Workbook

Sheet LEIA-ME
A1: Análise de Balanço de Cooperativa de Crédito: planilha de exercícios resolvidos
A3: Para que serve | B3: Esta planilha acompanha o material HTML 'Como analisar o BP de uma cooperativa de crédito'. Ela traz o BP e a DSP de exemplo, as notas, todos os indicadores e a resolução de cada exercício proposto, com fórmula e explicação.
A4: Cooperativa de exemplo | B4: Coop Vale do Ipê: cooperativa singular fictícia, filiada a uma central de um sistema cooperativo, segmento S4. Os números foram construídos para fins didáticos e fecham entre si (o balanço bate, a DSP explica o PL, os saldos médios explicam as receitas).
A5: Unidade | B5: Valores em R$ mil, salvo indicação. Ex.: 1.870.000 = R$ 1,87 bilhão.
A6: Cores | B6: Azul = dado digitado (pode mudar para simular). Preto = fórmula. Verde = link direto de outra aba. Amarelo = resposta do exercício.
A7: Fórmulas | B7: A coluna 'Fórmula (Excel PT-BR)' das abas de exercício mostra a fórmula como ela aparece no Excel em português (MÉDIA, SOMA, MÍNIMO, ponto e vírgula). O Excel converte automaticamente.
A8: Ordem sugerida | B8: 1) BP, DSP e Gerencial para conhecer a cooperativa. 2) Dados (notas). 3) Indicadores. 4) Ex01 a Ex15, na ordem do HTML. 5) Gabarito para conferir tudo de uma vez.
A9: Abas | B9: BP | DSP | Gerencial (DRE em cascata) | Dados (notas e premissas) | DMPL | RWA | Indicadores | Ex01 a Ex15 | Gabarito
A10: Ressalvas | B10: Os fatores de ponderação (FPR), o fator do risco operacional e as premissas de estresse do LCR são simplificações didáticas. Na cooperativa real, confira no DLO (documento 2061), no demonstrativo de RWA e na política de liquidez. A régua de 10,5% (8% + 2,5% de conservação) vale para o S4.
A11: Simule | B11: Troque um número azul (por exemplo, a despesa de PDD de 2025 na aba DSP) e veja ROE, IEAR, PL e Basileia mudarem juntos. É o melhor jeito de entender como as caixas se ligam.

Sheet BP
A1: Balanço Patrimonial: Coop Vale do Ipê (fictícia)
A2: Em R$ mil | posição em 31/12 | AV sobre o total do ativo (ou do passivo + PL) | AH = 2025 ÷ 2024 - 1
A4: Linha | B4: 31/12/2024 | C4: 31/12/2025 | D4: AV 2024 | E4: AV 2025 | F4: AH 25/24 | G4: Variação (R$ mil) | H4: O que entra
A5: ATIVO
A6: Disponibilidades (caixa) | B6: 28000 | C6: 31000 | D6: =IFERROR(B6/B$23,0) -> 0.010303436 | E6: =IFERROR(C6/C$23,0) -> 0.010045106 | F6: =IFERROR(C6/B6-1,"n.a.") -> 0.10714286 | G6: =C6-B6 -> 3000 | H6: Dinheiro em espécie nas agências e caixas eletrônicos.
A7: Centralização financeira (relações interfinanceiras) | B7: 695540 | C7: 789080 | D7: =IFERROR(B7/B$23,0) -> 0.25594471 | E7: =IFERROR(C7/C$23,0) -> 0.25569007 | F7: =IFERROR(C7/B7-1,"n.a.") -> 0.13448544 | G7: =C7-B7 -> 93540 | H7: Sobras de recursos aplicadas na Cooperativa Central. Principal reserva de liquidez; rende perto de 100% do CDI.
A8: Aplicações interfinanceiras de liquidez | B8: 60000 | C8: 85000 | D8: =IFERROR(B8/B$23,0) -> 0.022078792 | E8: =IFERROR(C8/C$23,0) -> 0.027543032 | F8: =IFERROR(C8/B8-1,"n.a.") -> 0.41666667 | G8: =C8-B8 -> 25000 | H8: Depósitos interfinanceiros aplicados (DI intrassistema, Banco Cooperativo) e compromissadas.
A9: Títulos e valores mobiliários | B9: 140000 | C9: 150000 | D9: =IFERROR(B9/B$23,0) -> 0.051517181 | E9: =IFERROR(C9/C$23,0) -> 0.04860535 | F9: =IFERROR(C9/B9-1,"n.a.") -> 0.071428571 | G9: =C9-B9 -> 10000 | H9: Títulos públicos federais e cotas de fundos de liquidez.
A10: Operações de crédito: empréstimos e títulos descontados | B10: 830000 | C10: 940000 | D10: =IFERROR(B10/B$23,0) -> 0.30542329 | E10: =IFERROR(C10/C$23,0) -> 0.30459353 | F10: =IFERROR(C10/B10-1,"n.a.") -> 0.13253012 | G10: =C10-B10 -> 110000 | H10: Crédito pessoal, consignado, cheque especial, capital de giro, desconto de títulos, cartão parcelado.
A11: Operações de crédito: financiamentos | B11: 290000 | C11: 340000 | D11: =IFERROR(B11/B$23,0) -> 0.10671416 | E11: =IFERROR(C11/C$23,0) -> 0.11017213 | F11: =IFERROR(C11/B11-1,"n.a.") -> 0.17241379 | G11: =C11-B11 -> 50000 | H11: Financiamento de veículos, imóveis, máquinas e investimentos de PJ (inclui repasses BNDES).
A12: Operações de crédito: financiamentos rurais e agroindustriais | B12: 520000 | C12: 590000 | D12: =IFERROR(B12/B$23,0) -> 0.19134953 | E12: =IFERROR(C12/C$23,0) -> 0.19118105 | F12: =IFERROR(C12/B12-1,"n.a.") -> 0.13461538 | G12: =C12-B12 -> 70000 | H12: Custeio, investimento e comercialização agrícola e pecuária; agroindústria.
A13: (=) Carteira de crédito bruta | B13: =B10+B11+B12 -> 1640000 | C13: =C10+C11+C12 -> 1870000 | D13: =IFERROR(B13/B$23,0) -> 0.60348698 | E13: =IFERROR(C13/C$23,0) -> 0.6059467 | F13: =IFERROR(C13/B13-1,"n.a.") -> 0.1402439 | G13: =C13-B13 -> 230000 | H13: Soma das operações de crédito antes da provisão.
A14: (-) Provisão para perdas esperadas (risco de crédito) | B14: -82000 | C14: -108000 | D14: =IFERROR(B14/B$23,0) -> -0.030174349 | E14: =IFERROR(C14/C$23,0) -> -0.034995852 | F14: =IFERROR(C14/B14-1,"n.a.") -> 0.31707317 | G14: =C14-B14 -> -26000 | H14: Perda esperada da carteira (Res. CMN 4.966). Conta redutora: negativa.
A15: (=) Carteira de crédito líquida | B15: =B13+B14 -> 1558000 | C15: =C13+C14 -> 1762000 | D15: =IFERROR(B15/B$23,0) -> 0.57331263 | E15: =IFERROR(C15/C$23,0) -> 0.57095085 | F15: =IFERROR(C15/B15-1,"n.a.") -> 0.1309371 | G15: =C15-B15 -> 204000 | H15: Carteira bruta menos provisão: o que se espera receber.
A16: Outros ativos financeiros | B16: 45000 | C16: 52000 | D16: =IFERROR(B16/B$23,0) -> 0.016559094 | E16: =IFERROR(C16/C$23,0) -> 0.016849855 | F16: =IFERROR(C16/B16-1,"n.a.") -> 0.15555556 | G16: =C16-B16 -> 7000 | H16: Rendas a receber, valores de cartões a receber, convênios, devedores diversos financeiros.
A17: Ativos fiscais (correntes e diferidos) | B17: 9000 | C17: 12000 | D17: =IFERROR(B17/B$23,0) -> 0.0033118188 | E17: =IFERROR(C17/C$23,0) -> 0.003888428 | F17: =IFERROR(C17/B17-1,"n.a.") -> 0.33333333 | G17: =C17-B17 -> 3000 | H17: Impostos a compensar e créditos tributários.
A18: Bens não de uso próprio (BNDU) | B18: 8000 | C18: 11000 | D18: =IFERROR(B18/B$23,0) -> 0.0029438389 | E18: =IFERROR(C18/C$23,0) -> 0.0035643924 | F18: =IFERROR(C18/B18-1,"n.a.") -> 0.375 | G18: =C18-B18 -> 3000 | H18: Bens recebidos em dação em pagamento, à venda.
A19: Outros ativos | B19: 13000 | C19: 15000 | D19: =IFERROR(B19/B$23,0) -> 0.0047837382 | E19: =IFERROR(C19/C$23,0) -> 0.004860535 | F19: =IFERROR(C19/B19-1,"n.a.") -> 0.15384615 | G19: =C19-B19 -> 2000 | H19: Despesas antecipadas, adiantamentos, materiais.
A20: Investimentos (participações no sistema) | B20: 95000 | C20: 104000 | D20: =IFERROR(B20/B$23,0) -> 0.034958087 | E20: =IFERROR(C20/C$23,0) -> 0.03369971 | F20: =IFERROR(C20/B20-1,"n.a.") -> 0.094736842 | G20: =C20-B20 -> 9000 | H20: Quotas da Central, da holding do sistema e de outras entidades.
A21: Imobilizado de uso | B21: 62000 | C21: 70000 | D21: =IFERROR(B21/B$23,0) -> 0.022814752 | E21: =IFERROR(C21/C$23,0) -> 0.022682497 | F21: =IFERROR(C21/B21-1,"n.a.") -> 0.12903226 | G21: =C21-B21 -> 8000 | H21: Agências, terrenos, móveis, equipamentos e TI, líquidos de depreciação.
A22: Intangível | B22: 4000 | C22: 5000 | D22: =IFERROR(B22/B$23,0) -> 0.0014719195 | E22: =IFERROR(C22/C$23,0) -> 0.0016201783 | F22: =IFERROR(C22/B22-1,"n.a.") -> 0.25 | G22: =C22-B22 -> 1000 | H22: Softwares e licenças. Deduzido do capital no PR.
A23: TOTAL DO ATIVO | B23: =B6+B7+B8+B9+B15+B16+B17+B18+B19+B20+B21+B22 -> 2717540 | C23: =C6+C7+C8+C9+C15+C16+C17+C18+C19+C20+C21+C22 -> 3086080 | D23: =IFERROR(B23/B$23,0) -> 1 | E23: =IFERROR(C23/C$23,0) -> 1 | F23: =IFERROR(C23/B23-1,"n.a.") -> 0.1356153 | G23: =C23-B23 -> 368540 | H23: Tudo o que a cooperativa tem ou tem a receber.
A24: PASSIVO
A25: Depósitos à vista | B25: 390000 | C25: 410000 | D25: =IFERROR(B25/B$44,0) -> 0.14351215 | E25: =IFERROR(C25/C$44,0) -> 0.13285462 | F25: =IFERROR(C25/B25-1,"n.a.") -> 0.051282051 | G25: =C25-B25 -> 20000 | H25: Saldo de conta corrente. Não paga juros; sai a qualquer momento.
A26: Depósitos de poupança | B26: 210000 | C26: 235000 | D26: =IFERROR(B26/B$44,0) -> 0.077275771 | E26: =IFERROR(C26/C$44,0) -> 0.076148382 | F26: =IFERROR(C26/B26-1,"n.a.") -> 0.11904762 | G26: =C26-B26 -> 25000 | H26: Poupança (inclui a rural). Remuneração da regra da poupança; parte é direcionada ao crédito rural.
A27: Depósitos a prazo (RDC) | B27: 1330000 | C27: 1520000 | D27: =IFERROR(B27/B$44,0) -> 0.48941322 | E27: =IFERROR(C27/C$44,0) -> 0.49253422 | F27: =IFERROR(C27/B27-1,"n.a.") -> 0.14285714 | G27: =C27-B27 -> 190000 | H27: Recibo de Depósito Cooperativo: depósito a prazo pago em % do CDI.
A28: (=) Total de depósitos | B28: =B25+B26+B27 -> 1930000 | C28: =C25+C26+C27 -> 2165000 | D28: =IFERROR(B28/B$44,0) -> 0.71020114 | E28: =IFERROR(C28/C$44,0) -> 0.70153723 | F28: =IFERROR(C28/B28-1,"n.a.") -> 0.12176166 | G28: =C28-B28 -> 235000 | H28: Depósitos totais dos associados.
A29: Recursos de aceites e emissão de títulos (LCA) | B29: 120000 | C29: 150000 | D29: =IFERROR(B29/B$44,0) -> 0.044157584 | E29: =IFERROR(C29/C$44,0) -> 0.04860535 | F29: =IFERROR(C29/B29-1,"n.a.") -> 0.25 | G29: =C29-B29 -> 30000 | H29: Letra de Crédito do Agronegócio emitida pela cooperativa.
A30: Relações interfinanceiras (repasses da Central e do Banco) | B30: 160000 | C30: 175000 | D30: =IFERROR(B30/B$44,0) -> 0.058876778 | E30: =IFERROR(C30/C$44,0) -> 0.056706242 | F30: =IFERROR(C30/B30-1,"n.a.") -> 0.09375 | G30: =C30-B30 -> 15000 | H30: Recursos tomados da Central e do Banco do sistema (inclui recursos para crédito rural e recursos corporativos).
A31: Obrigações por empréstimos e repasses (BNDES e outros) | B31: 120000 | C31: 140000 | D31: =IFERROR(B31/B$44,0) -> 0.044157584 | E31: =IFERROR(C31/C$44,0) -> 0.045364994 | F31: =IFERROR(C31/B31-1,"n.a.") -> 0.16666667 | G31: =C31-B31 -> 20000 | H31: BNDES, FINAME, BRDE, Funcafé e outros fundos repassados.
A32: Instrumentos de dívida elegíveis a capital (LFS) | B32: 0 | C32: 15000 | D32: =IFERROR(B32/B$44,0) -> 0 | E32: =IFERROR(C32/C$44,0) -> 0.004860535 | F32: =IFERROR(C32/B32-1,"n.a.") -> n.a. | G32: =C32-B32 -> 15000 | H32: Letra Financeira Subordinada: dívida longa que conta como capital (Nível II).
A33: Outros passivos financeiros | B33: 25000 | C33: 28000 | D33: =IFERROR(B33/B$44,0) -> 0.0091994966 | E33: =IFERROR(C33/C$44,0) -> 0.0090729988 | F33: =IFERROR(C33/B33-1,"n.a.") -> 0.12 | G33: =C33-B33 -> 3000 | H33: Cobrança e arrecadação de terceiros, valores a repassar de cartões.
A34: Provisões (contingências e garantias prestadas) | B34: 11000 | C34: 12000 | D34: =IFERROR(B34/B$44,0) -> 0.0040477785 | E34: =IFERROR(C34/C$44,0) -> 0.003888428 | F34: =IFERROR(C34/B34-1,"n.a.") -> 0.090909091 | G34: =C34-B34 -> 1000 | H34: Contingências trabalhistas, cíveis e fiscais e provisão para garantias financeiras prestadas.
A35: Obrigações sociais e estatutárias (FATES, sobras e quotas a pagar) | B35: 18000 | C35: 21000 | D35: =IFERROR(B35/B$44,0) -> 0.0066236376 | E35: =IFERROR(C35/C$44,0) -> 0.0068047491 | F35: =IFERROR(C35/B35-1,"n.a.") -> 0.16666667 | G35: =C35-B35 -> 3000 | H35: FATES, juros ao capital e sobras a pagar, quotas a devolver de associados desligados.
A36: Obrigações fiscais e outras obrigações | B36: 28000 | C36: 31000 | D36: =IFERROR(B36/B$44,0) -> 0.010303436 | E36: =IFERROR(C36/C$44,0) -> 0.010045106 | F36: =IFERROR(C36/B36-1,"n.a.") -> 0.10714286 | G36: =C36-B36 -> 3000 | H36: Tributos a recolher, salários e encargos, fornecedores.
A37: TOTAL DO PASSIVO | B37: =B28+B29+B30+B31+B32+B33+B34+B35+B36 -> 2412000 | C37: =C28+C29+C30+C31+C32+C33+C34+C35+C36 -> 2737000 | D37: =IFERROR(B37/B$44,0) -> 0.88756743 | E37: =IFERROR(C37/C$44,0) -> 0.88688563 | F37: =IFERROR(C37/B37-1,"n.a.") -> 0.13474295 | G37: =C37-B37 -> 325000 | H37: Obrigações com associados e terceiros.
A38: PATRIMÔNIO LÍQUIDO
A39: Capital social | B39: 130000 | C39: 159870 | D39: =IFERROR(B39/B$44,0) -> 0.047837382 | E39: =IFERROR(C39/C$44,0) -> 0.051803583 | F39: =IFERROR(C39/B39-1,"n.a.") -> 0.22976923 | G39: =C39-B39 -> 29870 | H39: Quotas-partes integralizadas pelos associados. Podem ser devolvidas quando o associado sai.
A40: Reserva legal | B40: 150000 | C40: 167870 | D40: =IFERROR(B40/B$44,0) -> 0.05519698 | E40: =IFERROR(C40/C$44,0) -> 0.054395868 | F40: =IFERROR(C40/B40-1,"n.a.") -> 0.11913333 | G40: =C40-B40 -> 17870 | H40: Parte das sobras retida por lei e estatuto. Capital mais estável.
A41: Sobras acumuladas (à disposição da AGO) | B41: 24540 | C41: 19840 | D41: =IFERROR(B41/B$44,0) -> 0.0090302259 | E41: =IFERROR(C41/C$44,0) -> 0.0064288677 | F41: =IFERROR(C41/B41-1,"n.a.") -> -0.19152404 | G41: =C41-B41 -> -4700 | H41: Sobras do ano ainda sem destino: a AGO decide (capital, conta corrente, reservas).
A42: Ajustes de avaliação patrimonial | B42: 1000 | C42: 1500 | D42: =IFERROR(B42/B$44,0) -> 0.00036797986 | E42: =IFERROR(C42/C$44,0) -> 0.0004860535 | F42: =IFERROR(C42/B42-1,"n.a.") -> 0.5 | G42: =C42-B42 -> 500 | H42: Marcação a mercado de títulos classificados em VJORA.
A43: TOTAL DO PATRIMÔNIO LÍQUIDO | B43: =B39+B40+B41+B42 -> 305540 | C43: =C39+C40+C41+C42 -> 349080 | D43: =IFERROR(B43/B$44,0) -> 0.11243257 | E43: =IFERROR(C43/C$44,0) -> 0.11311437 | F43: =IFERROR(C43/B43-1,"n.a.") -> 0.1425018 | G43: =C43-B43 -> 43540 | H43: Recursos próprios dos associados.
A44: TOTAL DO PASSIVO + PL | B44: =B37+B43 -> 2717540 | C44: =C37+C43 -> 3086080 | D44: =IFERROR(B44/B$44,0) -> 1 | E44: =IFERROR(C44/C$44,0) -> 1 | F44: =IFERROR(C44/B44-1,"n.a.") -> 0.1356153 | G44: =C44-B44 -> 368540
A45: Conferência: ativo - (passivo + PL) deve ser zero | B45: =B23-B44 -> 0 | C45: =C23-C44 -> 0
A46: FORA DO BALANÇO (contas de compensação)
A47: Coobrigações e garantias prestadas | B47: 180000 | C47: 210000 | F47: =IFERROR(C47/B47-1,"n.a.") -> 0.16666667 | G47: =C47-B47 -> 30000 | H47: Fianças e coobrigações em repasses. Não está no ativo, mas consome capital.

Sheet DSP
A1: Demonstração de Sobras ou Perdas (DSP): Coop Vale do Ipê
A2: Em R$ mil | exercícios de 2024 e 2025 | AV sobre o total das receitas da intermediação | despesas com sinal negativo
A4: Linha | B4: 2024 | C4: 2025 | D4: AV 2024 | E4: AV 2025 | F4: AH 25/24 | G4: Variação (R$ mil) | H4: O que entra
A5: RECEITAS (INGRESSOS) DA INTERMEDIAÇÃO FINANCEIRA
A6: Operações de crédito | B6: 290900 | C6: 345400 | D6: =IFERROR(B6/B$11,0) -> 0.74379954 | E6: =IFERROR(C6/C$11,0) -> 0.70203252 | F6: =IFERROR(C6/B6-1,"n.a.") -> 0.1873496 | G6: =C6-B6 -> 54500 | H6: Juros e encargos da carteira (comercial e rural). Ativo problemático (estágio 3) não gera receita até ser recebido.
A7: Recuperação de créditos baixados como prejuízo | B7: 7000 | C7: 9000 | D7: =IFERROR(B7/B$11,0) -> 0.017898236 | E7: =IFERROR(C7/C$11,0) -> 0.018292683 | F7: =IFERROR(C7/B7-1,"n.a.") -> 0.28571429 | G7: =C7-B7 -> 2000 | H7: Valores recebidos de créditos que já tinham sido baixados como perda.
A8: Ingressos de depósitos intercooperativos (centralização financeira) | B8: 72800 | C8: 106200 | D8: =IFERROR(B8/B$11,0) -> 0.18614165 | E8: =IFERROR(C8/C$11,0) -> 0.21585366 | F8: =IFERROR(C8/B8-1,"n.a.") -> 0.45879121 | G8: =C8-B8 -> 33400 | H8: Rendimento da centralização financeira na Central.
A9: Resultado de aplicações interfinanceiras de liquidez | B9: 6200 | C9: 10700 | D9: =IFERROR(B9/B$11,0) -> 0.015852723 | E9: =IFERROR(C9/C$11,0) -> 0.021747967 | F9: =IFERROR(C9/B9-1,"n.a.") -> 0.72580645 | G9: =C9-B9 -> 4500 | H9: Rendimento do DI aplicado e de outras aplicações interfinanceiras.
A10: Resultado de operações com títulos e valores mobiliários | B10: 14200 | C10: 20700 | D10: =IFERROR(B10/B$11,0) -> 0.03630785 | E10: =IFERROR(C10/C$11,0) -> 0.042073171 | F10: =IFERROR(C10/B10-1,"n.a.") -> 0.45774648 | G10: =C10-B10 -> 6500 | H10: Rendimento dos títulos e fundos.
A11: (=) Total das receitas da intermediação | B11: =B6+B7+B8+B9+B10 -> 391100 | C11: =C6+C7+C8+C9+C10 -> 492000 | D11: =IFERROR(B11/B$11,0) -> 1 | E11: =IFERROR(C11/C$11,0) -> 1 | F11: =IFERROR(C11/B11-1,"n.a.") -> 0.25799028 | G11: =C11-B11 -> 100900
A12: DESPESAS (DISPÊNDIOS) DA INTERMEDIAÇÃO FINANCEIRA
A13: Despesas de depósitos de poupança | B13: -15200 | C13: -18500 | D13: =IFERROR(B13/B$11,0) -> -0.03886474 | E13: =IFERROR(C13/C$11,0) -> -0.037601626 | F13: =IFERROR(C13/B13-1,"n.a.") -> 0.21710526 | G13: =C13-B13 -> -3300 | H13: Remuneração paga na poupança.
A14: Despesas de depósitos a prazo (RDC) | B14: -137600 | C14: -205900 | D14: =IFERROR(B14/B$11,0) -> -0.35182818 | E14: =IFERROR(C14/C$11,0) -> -0.41849593 | F14: =IFERROR(C14/B14-1,"n.a.") -> 0.49636628 | G14: =C14-B14 -> -68300 | H14: Juros pagos (ou apropriados) no RDC.
A15: Despesas de LCA | B15: -10900 | C15: -17800 | D15: =IFERROR(B15/B$11,0) -> -0.02787011 | E15: =IFERROR(C15/C$11,0) -> -0.036178862 | F15: =IFERROR(C15/B15-1,"n.a.") -> 0.63302752 | G15: =C15-B15 -> -6900 | H15: Juros pagos na LCA.
A16: Despesas de LFS | B16: 0 | C16: -1600 | D16: =IFERROR(B16/B$11,0) -> 0 | E16: =IFERROR(C16/C$11,0) -> -0.0032520325 | F16: =IFERROR(C16/B16-1,"n.a.") -> n.a. | G16: =C16-B16 -> -1600 | H16: Juros da LFS.
A17: Contribuição ao FGCoop | B17: -2800 | C17: -3300 | D17: =IFERROR(B17/B$11,0) -> -0.0071592943 | E17: =IFERROR(C17/C$11,0) -> -0.0067073171 | F17: =IFERROR(C17/B17-1,"n.a.") -> 0.17857143 | G17: =C17-B17 -> -500 | H17: Contribuição ordinária ao Fundo Garantidor do Cooperativismo de Crédito.
A18: (=) Operações de captação no mercado | B18: =B13+B14+B15+B16+B17 -> -166500 | C18: =C13+C14+C15+C16+C17 -> -247100 | D18: =IFERROR(B18/B$11,0) -> -0.42572232 | E18: =IFERROR(C18/C$11,0) -> -0.50223577 | F18: =IFERROR(C18/B18-1,"n.a.") -> 0.48408408 | G18: =C18-B18 -> -80600
A19: Repasses interfinanceiros (Central e Banco) | B19: -14300 | C19: -18400 | D19: =IFERROR(B19/B$11,0) -> -0.036563539 | E19: =IFERROR(C19/C$11,0) -> -0.037398374 | F19: =IFERROR(C19/B19-1,"n.a.") -> 0.28671329 | G19: =C19-B19 -> -4100 | H19: Custo dos recursos tomados da Central e do Banco.
A20: Empréstimos e repasses (BNDES e outros) | B20: -10100 | C20: -12700 | D20: =IFERROR(B20/B$11,0) -> -0.025824597 | E20: =IFERROR(C20/C$11,0) -> -0.025813008 | F20: =IFERROR(C20/B20-1,"n.a.") -> 0.25742574 | G20: =C20-B20 -> -2600 | H20: Custo dos repasses BNDES e outros fundos.
A21: (=) Operações de empréstimos e repasses | B21: =B19+B20 -> -24400 | C21: =C19+C20 -> -31100 | D21: =IFERROR(B21/B$11,0) -> -0.062388136 | E21: =IFERROR(C21/C$11,0) -> -0.063211382 | F21: =IFERROR(C21/B21-1,"n.a.") -> 0.27459016 | G21: =C21-B21 -> -6700
A22: Provisão para perdas esperadas associadas ao risco de crédito | B22: -46000 | C22: -64000 | D22: =IFERROR(B22/B$11,0) -> -0.11761698 | E22: =IFERROR(C22/C$11,0) -> -0.1300813 | F22: =IFERROR(C22/B22-1,"n.a.") -> 0.39130435 | G22: =C22-B22 -> -18000 | H22: Despesa de provisão para perdas esperadas do período.
A23: (=) Total das despesas da intermediação | B23: =B18+B21+B22 -> -236900 | C23: =C18+C21+C22 -> -342200 | D23: =IFERROR(B23/B$11,0) -> -0.60572744 | E23: =IFERROR(C23/C$11,0) -> -0.69552846 | F23: =IFERROR(C23/B23-1,"n.a.") -> 0.44449135 | G23: =C23-B23 -> -105300
A24: RESULTADO BRUTO DA INTERMEDIAÇÃO FINANCEIRA | B24: =B11+B23 -> 154200 | C24: =C11+C23 -> 149800 | D24: =IFERROR(B24/B$11,0) -> 0.39427256 | E24: =IFERROR(C24/C$11,0) -> 0.30447154 | F24: =IFERROR(C24/B24-1,"n.a.") -> -0.028534371 | G24: =C24-B24 -> -4400
A25: OUTRAS RECEITAS E DESPESAS OPERACIONAIS
A26: Receitas de prestação de serviços | B26: 41000 | C26: 48000 | D26: =IFERROR(B26/B$11,0) -> 0.10483252 | E26: =IFERROR(C26/C$11,0) -> 0.097560976 | F26: =IFERROR(C26/B26-1,"n.a.") -> 0.17073171 | G26: =C26-B26 -> 7000 | H26: Cartões, seguros, consórcios, cobrança, comissões.
A27: Rendas de tarifas | B27: 12500 | C27: 14000 | D27: =IFERROR(B27/B$11,0) -> 0.031961135 | E27: =IFERROR(C27/C$11,0) -> 0.028455285 | F27: =IFERROR(C27/B27-1,"n.a.") -> 0.12 | G27: =C27-B27 -> 1500 | H27: Tarifas de conta e pacotes de serviços.
A28: Despesas de pessoal | B28: -78000 | C28: -86000 | D28: =IFERROR(B28/B$11,0) -> -0.19943748 | E28: =IFERROR(C28/C$11,0) -> -0.17479675 | F28: =IFERROR(C28/B28-1,"n.a.") -> 0.1025641 | G28: =C28-B28 -> -8000 | H28: Salários, encargos, benefícios, PLR e treinamento.
A29: Outras despesas administrativas | B29: -60000 | C29: -66000 | D29: =IFERROR(B29/B$11,0) -> -0.15341345 | E29: =IFERROR(C29/C$11,0) -> -0.13414634 | F29: =IFERROR(C29/B29-1,"n.a.") -> 0.1 | G29: =C29-B29 -> -6000 | H29: TI, aluguéis, depreciação, marketing, transporte de valores, rateios da Central e da Confederação.
A30: Despesas tributárias | B30: -4700 | C30: -5400 | D30: =IFERROR(B30/B$11,0) -> -0.012017387 | E30: =IFERROR(C30/C$11,0) -> -0.01097561 | F30: =IFERROR(C30/B30-1,"n.a.") -> 0.14893617 | G30: =C30-B30 -> -700 | H30: PIS, Cofins e ISS (principalmente sobre atos não cooperativos e serviços).
A31: Outras receitas operacionais | B31: 6500 | C31: 7500 | D31: =IFERROR(B31/B$11,0) -> 0.01661979 | E31: =IFERROR(C31/C$11,0) -> 0.015243902 | F31: =IFERROR(C31/B31-1,"n.a.") -> 0.15384615 | G31: =C31-B31 -> 1000 | H31: Juros ao capital recebidos de participações, recuperação de encargos e outras.
A32: Outras despesas operacionais | B32: -11500 | C32: -13500 | D32: =IFERROR(B32/B$11,0) -> -0.029404244 | E32: =IFERROR(C32/C$11,0) -> -0.027439024 | F32: =IFERROR(C32/B32-1,"n.a.") -> 0.17391304 | G32: =C32-B32 -> -2000 | H32: Despesas com cartões, perdas operacionais, descontos concedidos e outras.
A33: Provisões para contingências e garantias (líquidas) | B33: -1200 | C33: 1800 | D33: =IFERROR(B33/B$11,0) -> -0.003068269 | E33: =IFERROR(C33/C$11,0) -> 0.0036585366 | F33: =IFERROR(C33/B33-1,"n.a.") -> -2.5 | G33: =C33-B33 -> 3000 | H33: Constituição (-) ou reversão (+) de provisões para contingências e garantias.
A34: (=) Total de outras receitas e despesas operacionais | B34: =B26+B27+B28+B29+B30+B31+B32+B33 -> -95400 | C34: =C26+C27+C28+C29+C30+C31+C32+C33 -> -99600 | D34: =IFERROR(B34/B$11,0) -> -0.24392738 | E34: =IFERROR(C34/C$11,0) -> -0.20243902 | F34: =IFERROR(C34/B34-1,"n.a.") -> 0.044025157 | G34: =C34-B34 -> -4200
A35: RESULTADO OPERACIONAL | B35: =B24+B34 -> 58800 | C35: =C24+C34 -> 50200 | D35: =IFERROR(B35/B$11,0) -> 0.15034518 | E35: =IFERROR(C35/C$11,0) -> 0.10203252 | F35: =IFERROR(C35/B35-1,"n.a.") -> -0.1462585 | G35: =C35-B35 -> -8600
A36: Resultado não operacional | B36: 300 | C36: 4200 | D36: =IFERROR(B36/B$11,0) -> 0.00076706725 | E36: =IFERROR(C36/C$11,0) -> 0.0085365854 | F36: =IFERROR(C36/B36-1,"n.a.") -> 13 | G36: =C36-B36 -> 3900 | H36: Ganho ou perda na venda de bens (imóveis, BNDU).
A37: RESULTADO ANTES DA TRIBUTAÇÃO | B37: =B35+B36 -> 59100 | C37: =C35+C36 -> 54400 | D37: =IFERROR(B37/B$11,0) -> 0.15111225 | E37: =IFERROR(C37/C$11,0) -> 0.11056911 | F37: =IFERROR(C37/B37-1,"n.a.") -> -0.079526227 | G37: =C37-B37 -> -4700
A38: IR e CS sobre atos não cooperativos | B38: -600 | C38: -700 | D38: =IFERROR(B38/B$11,0) -> -0.0015341345 | E38: =IFERROR(C38/C$11,0) -> -0.0014227642 | F38: =IFERROR(C38/B38-1,"n.a.") -> 0.16666667 | G38: =C38-B38 -> -100 | H38: Tributos sobre o resultado de atos não cooperativos.
A39: RESULTADO ANTES DOS JUROS AO CAPITAL (sobras brutas) | B39: =B37+B38 -> 58500 | C39: =C37+C38 -> 53700 | D39: =IFERROR(B39/B$11,0) -> 0.14957811 | E39: =IFERROR(C39/C$11,0) -> 0.10914634 | F39: =IFERROR(C39/B39-1,"n.a.") -> -0.082051282 | G39: =C39-B39 -> -4800 | H39: Base do ROE: resultado gerado antes de remunerar as quotas.
A40: Juros ao capital | B40: -8200 | C40: -12600 | D40: =IFERROR(B40/B$11,0) -> -0.020966505 | E40: =IFERROR(C40/C$11,0) -> -0.025609756 | F40: =IFERROR(C40/B40-1,"n.a.") -> 0.53658537 | G40: =C40-B40 -> -4400 | H40: Remuneração das quotas-partes (limitada à Selic pela LC 130/2009).
A41: SOBRAS DO EXERCÍCIO APÓS JUROS AO CAPITAL | B41: =B39+B40 -> 50300 | C41: =C39+C40 -> 41100 | D41: =IFERROR(B41/B$11,0) -> 0.12861161 | E41: =IFERROR(C41/C$11,0) -> 0.083536585 | F41: =IFERROR(C41/B41-1,"n.a.") -> -0.18290258 | G41: =C41-B41 -> -9200
A42: DESTINAÇÕES
A43: FATES: resultado de atos não cooperativos | B43: -1200 | C43: -1400 | D43: =IFERROR(B43/B$11,0) -> -0.003068269 | E43: =IFERROR(C43/C$11,0) -> -0.0028455285 | F43: =IFERROR(C43/B43-1,"n.a.") -> 0.16666667 | G43: =C43-B43 -> -200 | H43: Resultado de atos não cooperativos vai inteiro para o FATES (Lei 5.764, art. 87).
A44: Reserva legal (45% da base) | B44: =-ROUND((B41+B43)*Dados!$B$84,-1) -> -22100 | C44: =-ROUND((C41+C43)*Dados!$B$84,-1) -> -17870 | D44: =IFERROR(B44/B$11,0) -> -0.056507287 | E44: =IFERROR(C44/C$11,0) -> -0.036321138 | F44: =IFERROR(C44/B44-1,"n.a.") -> -0.19140271 | G44: =C44-B44 -> 4230 | H44: Percentual do estatuto sobre a base (lei: mínimo de 10%).
A45: FATES estatutário (5% da base) | B45: =-ROUND((B41+B43)*Dados!$B$85,-1) -> -2460 | C45: =-ROUND((C41+C43)*Dados!$B$85,-1) -> -1990 | D45: =IFERROR(B45/B$11,0) -> -0.0062899514 | E45: =IFERROR(C45/C$11,0) -> -0.0040447154 | F45: =IFERROR(C45/B45-1,"n.a.") -> -0.19105691 | G45: =C45-B45 -> 470 | H45: Percentual do estatuto sobre a base (lei: mínimo de 5%).
A46: SOBRAS À DISPOSIÇÃO DA AGO | B46: =B41+B43+B44+B45 -> 24540 | C46: =C41+C43+C44+C45 -> 19840 | D46: =IFERROR(B46/B$11,0) -> 0.062746101 | E46: =IFERROR(C46/C$11,0) -> 0.040325203 | F46: =IFERROR(C46/B46-1,"n.a.") -> -0.19152404 | G46: =C46-B46 -> -4700 | H46: A AGO decide: capitalizar, distribuir em conta ou reforçar reservas.
A48: Conferência: sobras à disposição da AGO = sobras acumuladas do BP | B48: =B46-BP!$B$41 -> 0 | C48: =C46-BP!$C$41 -> 0

Sheet Gerencial
A1: DRE gerencial em cascata (a mesma DSP, arrumada para análise)
A2: Em R$ mil | é a visão do simulador de resultado: margem financeira, receita líquida, custo e risco
A4: Linha | B4: 2024 | C4: 2025 | D4: AH 25/24 | E4: Como se calcula
A5: Receita de crédito | B5: =DSP!$B$6 -> 290900 | C5: =DSP!$C$6 -> 345400 | D5: =IFERROR(C5/B5-1,"n.a.") -> 0.1873496 | E5: Operações de crédito da DSP
A6: (+) Receita da liquidez | B6: =DSP!$B$8+DSP!$B$9+DSP!$B$10 -> 93200 | C6: =DSP!$C$8+DSP!$C$9+DSP!$C$10 -> 137600 | D6: =IFERROR(C6/B6-1,"n.a.") -> 0.47639485 | E6: Centralização + aplicações interfinanceiras + TVM
A7: (-) Despesa de captação | B7: =DSP!$B$18 -> -166500 | C7: =DSP!$C$18 -> -247100 | D7: =IFERROR(C7/B7-1,"n.a.") -> 0.48408408 | E7: Poupança, RDC, LCA, LFS e FGCoop
A8: (-) Despesa de repasses | B8: =DSP!$B$21 -> -24400 | C8: =DSP!$C$21 -> -31100 | D8: =IFERROR(C8/B8-1,"n.a.") -> 0.27459016 | E8: Central, Banco e BNDES
A9: (=) MARGEM FINANCEIRA | B9: =SUM(B5:B8) -> 193200 | C9: =SUM(C5:C8) -> 204800 | D9: =IFERROR(C9/B9-1,"n.a.") -> 0.060041408 | E9: Antes da PDD. É o 'spread' da cooperativa inteira
A10: (+) Serviços e tarifas | B10: =DSP!$B$26+DSP!$B$27 -> 53500 | C10: =DSP!$C$26+DSP!$C$27 -> 62000 | D10: =IFERROR(C10/B10-1,"n.a.") -> 0.1588785
A11: (+/-) Outras receitas e despesas operacionais | B11: =DSP!$B$31+DSP!$B$32+DSP!$B$30+DSP!$B$33 -> -10900 | C11: =DSP!$C$31+DSP!$C$32+DSP!$C$30+DSP!$C$33 -> -9600 | D11: =IFERROR(C11/B11-1,"n.a.") -> -0.11926606 | E11: Outras receitas - outras despesas - tributárias +/- contingências
A12: (=) RECEITA LÍQUIDA (base do índice de eficiência) | B12: =B9+B10+B11 -> 235800 | C12: =C9+C10+C11 -> 257200 | D12: =IFERROR(C12/B12-1,"n.a.") -> 0.090754877 | E12: Margem + serviços + outras
A13: (-) Despesas administrativas | B13: =DSP!$B$28+DSP!$B$29 -> -138000 | C13: =DSP!$C$28+DSP!$C$29 -> -152000 | D13: =IFERROR(C13/B13-1,"n.a.") -> 0.10144928 | E13: Pessoal + outras administrativas
A14: (-) PDD líquida de recuperações | B14: =DSP!$B$22+DSP!$B$7 -> -39000 | C14: =DSP!$C$22+DSP!$C$7 -> -55000 | D14: =IFERROR(C14/B14-1,"n.a.") -> 0.41025641 | E14: Custo do risco de crédito do ano
A15: (=) RESULTADO OPERACIONAL | B15: =B12+B13+B14 -> 58800 | C15: =C12+C13+C14 -> 50200 | D15: =IFERROR(C15/B15-1,"n.a.") -> -0.1462585
A16: (+/-) Resultado não operacional | B16: =DSP!$B$36 -> 300 | C16: =DSP!$C$36 -> 4200 | D16: =IFERROR(C16/B16-1,"n.a.") -> 13
A17: (-) IR e CS | B17: =DSP!$B$38 -> -600 | C17: =DSP!$C$38 -> -700 | D17: =IFERROR(C17/B17-1,"n.a.") -> 0.16666667
A18: (=) RESULTADO ANTES DOS JUROS AO CAPITAL | B18: =B15+B16+B17 -> 58500 | C18: =C15+C16+C17 -> 53700 | D18: =IFERROR(C18/B18-1,"n.a.") -> -0.082051282 | E18: Base do ROE
A19: Conferência com a DSP (deve ser zero) | B19: =B18-DSP!$B$39 -> 0 | C19: =C18-DSP!$C$39 -> 0
A20: (-) Itens não recorrentes (notas) | B20: =Dados!$C$66 -> -2200 | C20: =Dados!$D$66 -> 9200 | D20: =IFERROR(C20/B20-1,"n.a.") -> -5.1818182 | E20: Ganhos e perdas que não se repetem
A21: (=) RESULTADO RECORRENTE | B21: =B18-B20 -> 60700 | C21: =C18-C20 -> 44500 | D21: =IFERROR(C21/B21-1,"n.a.") -> -0.26688633 | E21: Resultado que tende a se repetir

Sheet Dados
A1: Notas explicativas e premissas da Coop Vale do Ipê
A2: Em R$ mil, salvo indicação. Azul = dado digitado; verde = link; preto = fórmula.
A3: Item | B3: 2023 / valor | C3: 2024 | D3: 2025 | E3: Nota
A4: PREMISSAS MACRO
A5: CDI médio do ano | C5: 0.109 | D5: 0.143 | E5: Premissa do exemplo (aproximada)
A6: IPCA do ano | C6: 0.048 | D6: 0.045 | E6: Premissa do exemplo
A8: SALDOS PARA MÉDIAS (2023 digitado; 2024 e 2025 ligados ao BP)
A9: Ativo total | B9: 2390000 | C9: =BP!$B$23 -> 2717540 | D9: =BP!$C$23 -> 3086080
A10: Disponibilidades | B10: 25000 | C10: =BP!$B$6 -> 28000 | D10: =BP!$C$6 -> 31000
A11: Centralização financeira | B11: 640000 | C11: =BP!$B$7 -> 695540 | D11: =BP!$C$7 -> 789080
A12: Aplicações interfinanceiras | B12: 50000 | C12: =BP!$B$8 -> 60000 | D12: =BP!$C$8 -> 85000
A13: TVM | B13: 120000 | C13: =BP!$B$9 -> 140000 | D13: =BP!$C$9 -> 150000
A14: Liquidez rentável (centralização + aplicações + TVM) | B14: =Dados!$B$11+Dados!$B$12+Dados!$B$13 -> 810000 | C14: =Dados!$C$11+Dados!$C$12+Dados!$C$13 -> 895540 | D14: =Dados!$D$11+Dados!$D$12+Dados!$D$13 -> 1024080
A15: Liquidez total (caixa + liquidez rentável) | B15: =Dados!$B$10+Dados!$B$14 -> 835000 | C15: =Dados!$C$10+Dados!$C$14 -> 923540 | D15: =Dados!$D$10+Dados!$D$14 -> 1055080
A16: Carteira comercial (empréstimos + financiamentos) | B16: 990000 | C16: =BP!$B$10+BP!$B$11 -> 1120000 | D16: =BP!$C$10+BP!$C$11 -> 1280000
A17: Carteira rural | B17: 460000 | C17: =BP!$B$12 -> 520000 | D17: =BP!$C$12 -> 590000
A18: Carteira bruta | B18: =Dados!$B$16+Dados!$B$17 -> 1450000 | C18: =BP!$B$13 -> 1640000 | D18: =BP!$C$13 -> 1870000
A19: Provisão (negativa) | B19: -68000 | C19: =BP!$B$14 -> -82000 | D19: =BP!$C$14 -> -108000
A20: Depósitos à vista | B20: 360000 | C20: =BP!$B$25 -> 390000 | D20: =BP!$C$25 -> 410000
A21: Poupança | B21: 190000 | C21: =BP!$B$26 -> 210000 | D21: =BP!$C$26 -> 235000
A22: RDC | B22: 1150000 | C22: =BP!$B$27 -> 1330000 | D22: =BP!$C$27 -> 1520000
A23: Depósitos totais | B23: =Dados!$B$20+Dados!$B$21+Dados!$B$22 -> 1700000 | C23: =BP!$B$28 -> 1930000 | D23: =BP!$C$28 -> 2165000
A24: LCA | B24: 95000 | C24: =BP!$B$29 -> 120000 | D24: =BP!$C$29 -> 150000
A25: Captação com associados (depósitos + LCA) | B25: =Dados!$B$23+Dados!$B$24 -> 1795000 | C25: =Dados!$C$23+Dados!$C$24 -> 2050000 | D25: =Dados!$D$23+Dados!$D$24 -> 2315000
A26: Repasses interfinanceiros | B26: 140000 | C26: =BP!$B$30 -> 160000 | D26: =BP!$C$30 -> 175000
A27: Empréstimos e repasses | B27: 105000 | C27: =BP!$B$31 -> 120000 | D27: =BP!$C$31 -> 140000
A28: LFS | B28: 0 | C28: =BP!$B$32 -> 0 | D28: =BP!$C$32 -> 15000
A29: Patrimônio líquido | B29: 280000 | C29: =BP!$B$43 -> 305540 | D29: =BP!$C$43 -> 349080
A30: Capital social | B30: 120000 | C30: =BP!$B$39 -> 130000 | D30: =BP!$C$39 -> 159870
A32: CARTEIRA POR FAIXA DE ATRASO (saldo bruto)
A33: Em dia | C33: 1548000 | D33: 1735000
A34: 1 a 14 dias | C34: 25000 | D34: 30000
A35: 15 a 30 dias | C35: 16000 | D35: 20000
A36: 31 a 60 dias | C36: 12000 | D36: 18000
A37: 61 a 90 dias | C37: 8000 | D37: 12000
A38: Acima de 90 dias | C38: 31000 | D38: 55000
A39: Total (confere com a carteira do BP) | C39: =SUM(C33:C38) -> 1640000 | D39: =SUM(D33:D38) -> 1870000
A41: CARTEIRA POR ESTÁGIO (Res. CMN 4.966)
A42: Estágio 1: saldo | C42: 1462000 | D42: 1640000
A43: Estágio 2: saldo | C43: 120000 | D43: 150000
A44: Estágio 3: saldo | C44: 58000 | D44: 80000
A45: Estágio 1: provisão | C45: 21930 | D45: 26240
A46: Estágio 2: provisão | C46: 13200 | D46: 18000
A47: Estágio 3: provisão | C47: 46870 | D47: 63760
A48: Provisão da carteira comercial | C48: 70000 | D48: 92000
A49: Provisão da carteira rural | C49: 12000 | D49: 16000
A50: Operações renegociadas no ano (saldo) | C50: 41000 | D50: 62000
A51: 20 maiores devedores ÷ carteira | C51: 0.06 | D51: 0.065
A53: RECEITA DE CRÉDITO POR CARTEIRA (detalhe da DSP)
A54: Receita da carteira comercial | C54: 232100 | D54: 276000
A55: Receita da carteira rural | C55: 58800 | D55: 69400
A57: ASSOCIADOS E CONCENTRAÇÃO
A58: Associados (quantidade) | B58: 91000 | C58: 98000 | D58: 106000
A59: 10 maiores depositantes ÷ captação | C59: 0.08 | D59: 0.095
A61: ITENS NÃO RECORRENTES (efeito no resultado: + ganho, - perda)
A62: Programa de desligamento voluntário (em despesas de pessoal) | C62: -2500 | D62: 0
A63: Venda de imóvel de agência (resultado não operacional) | C63: 300 | D63: 4200
A64: Reversão de contingência fiscal ganha (em contingências) | C64: 0 | D64: 3000
A65: Recuperação extraordinária de um grande crédito baixado | C65: 0 | D65: 2000
A66: Total de itens não recorrentes | C66: =SUM(C62:C65) -> -2200 | D66: =SUM(D62:D65) -> 9200
A68: DETALHE DE DESPESAS ADMINISTRATIVAS
A69: Depreciação e amortização (dentro de outras despesas administrativas) | C69: 6800 | D69: 7500
A70: Rateios da Central e da Confederação (dentro de outras despesas administrativas) | C70: 15500 | D70: 18000
A72: CAPITAL REGULATÓRIO (premissas)
A73: RWA de risco de mercado (informado) | C73: 3000 | D73: 4000
A74: Outros ajustes prudenciais (além do intangível) | C74: 3000 | D74: 3000
A75: Receita bruta para risco operacional (margem financeira + serviços e tarifas) | C75: =Gerencial!$B$9+Gerencial!$B$10 -> 246700 | D75: =Gerencial!$C$9+Gerencial!$C$10 -> 266800 | E75: 2024 e 2025 = margem financeira + serviços e tarifas (aba Gerencial)
A76: Receita bruta de 2022 | B76: 160000
A77: Receita bruta de 2023 | B77: 180000
A78: Fator do risco operacional (abordagem simplificada) | B78: 0.15 | E78: Didático: 15% da receita bruta média
A79: Fator F (exigência básica de PR) | B79: 0.08
A80: Exigência de PR + adicional de conservação (S4) | B80: 0.105 | E80: 8% + 2,5%
A81: Piso gerencial de MM/RWA (política de recursos corporativos) | B81: 0.02 | E81: Aula de Recursos Corporativos: 2 p.p.
A82: FPR usado na conta do potencial de crédito (política) | B82: 1.1
A83: Nível mínimo de liquidez (NML) sobre depósitos | B83: 0.3 | E83: Ilustrativo
A84: Destinação à reserva legal (estatuto) | B84: 0.45 | E84: Lei 5.764: mínimo de 10%
A85: Destinação ao FATES (estatuto) | B85: 0.05 | E85: Lei 5.764: mínimo de 5%
A87: FATORES DE PONDERAÇÃO DE RISCO (FPR, ilustrativos)
A88: FPR: Disponibilidades | B88: 0
A89: FPR: Centralização financeira | B89: 0.2
A90: FPR: Aplicações interfinanceiras | B90: 0.2
A91: FPR: Títulos públicos federais | B91: 0
A92: FPR: Carteira comercial (líquida de provisão) | B92: 0.85
A93: FPR: Carteira rural (líquida de provisão) | B93: 0.75
A94: FPR: Outros ativos financeiros | B94: 1
A95: FPR: Ativos fiscais | B95: 1
A96: FPR: BNDU e outros ativos | B96: 1
A97: FPR: Investimentos | B97: 1
A98: FPR: Imobilizado | B98: 1
A99: FPR: Coobrigações e garantias (fora do balanço) | B99: 0.75
A101: FTP: TAXAS DE TRANSFERÊNCIA (anuais)
A102: FTP: Crédito comercial (paga à tesouraria) | C102: 0.116 | D102: 0.15
A103: FTP: Crédito rural (paga à tesouraria) | C103: 0.09 | D103: 0.108
A104: FTP: Depósito à vista, parcela estável (recebe da tesouraria) | C104: 0.098 | D104: 0.129
A105: FTP: Poupança (recebe) | C105: 0.094 | D105: 0.12
A106: FTP: RDC (recebe) | C106: 0.109 | D106: 0.143
A107: FTP: LCA (recebe) | C107: 0.104 | D107: 0.136
A109: RAROC POR CARTEIRA (premissas de 2025)
A110: Custo operacional alocado: comercial (% do saldo médio) | B110: 0.035
A111: Custo operacional alocado: rural | B111: 0.015
...

Sheet DMPL
A1: Demonstração das mutações do PL em 2025 (DMPL)
A2: Em R$ mil | cada linha mostra o efeito em cada conta do PL
A4: Evento | B4: Capital social | C4: Reserva legal | D4: Sobras acumuladas | E4: Ajustes de avaliação | F4: Total do PL | G4: Explicação
A5: Saldo em 31/12/2024 | B5: =BP!$B$39 -> 130000 | C5: =BP!$B$40 -> 150000 | D5: =BP!$B$41 -> 24540 | E5: =BP!$B$42 -> 1000 | F5: =SUM(B5:E5) -> 305540 | G5: Vem do BP de 2024
A6: Integralizações de capital | B6: =Dados!$B$132 -> 14000 | C6: 0 | D6: 0 | E6: 0 | F6: =SUM(B6:E6) -> 14000 | G6: Novos associados e aportes
A7: Devoluções de quotas | B7: =Dados!$B$133 -> -9000 | C7: 0 | D7: 0 | E7: 0 | F7: =SUM(B7:E7) -> -9000 | G7: Associados que saíram levam a quota
A8: AGO: capitalização de sobras de 2024 | B8: =ROUND(BP!$B$41*Dados!$B$134,-1) -> 12270 | C8: 0 | D8: =-B8 -> -12270 | E8: 0 | F8: =SUM(B8:E8) -> 0 | G8: Sai das sobras, entra no capital: PL não muda
A9: AGO: sobras de 2024 creditadas em conta corrente | B9: 0 | C9: 0 | D9: =-(BP!$B$41+D8) -> -12270 | E9: 0 | F9: =SUM(B9:E9) -> -12270 | G9: Sai do PL e vira depósito à vista
A10: Resultado do exercício (antes dos juros ao capital) | B10: 0 | C10: 0 | D10: =DSP!$C$39 -> 53700 | E10: 0 | F10: =SUM(B10:E10) -> 53700 | G10: DSP de 2025
A11: Juros ao capital: destinação | B11: 0 | C11: 0 | D11: =DSP!$C$40 -> -12600 | E11: 0 | F11: =SUM(B11:E11) -> -12600 | G11: Remuneração das quotas
A12: Juros ao capital: incorporação às quotas | B12: =-DSP!$C$40 -> 12600 | C12: 0 | D12: 0 | E12: 0 | F12: =SUM(B12:E12) -> 12600 | G12: Creditados no capital do associado: efeito zero no PL
A13: FATES (ato não cooperativo + estatutário) | B13: 0 | C13: 0 | D13: =DSP!$C$43+DSP!$C$45 -> -3390 | E13: 0 | F13: =SUM(B13:E13) -> -3390 | G13: Vai para o passivo (obrigações sociais)
A14: Reserva legal | B14: 0 | C14: =-DSP!$C$44 -> 17870 | D14: =DSP!$C$44 -> -17870 | E14: 0 | F14: =SUM(B14:E14) -> 0 | G14: Sai das sobras, entra na reserva
A15: Ajuste de avaliação patrimonial do ano | B15: 0 | C15: 0 | D15: 0 | E15: =BP!$C$42-BP!$B$42 -> 500 | F15: =SUM(B15:E15) -> 500 | G15: Marcação a mercado (VJORA)
A16: Saldo em 31/12/2025 | B16: =SUM(B5:B15) -> 159870 | C16: =SUM(C5:C15) -> 167870 | D16: =SUM(D5:D15) -> 19840 | E16: =SUM(E5:E15) -> 1500 | F16: =SUM(B16:E16) -> 349080 | G16: Soma das linhas
A17: Conferência com o BP de 2025 (deve ser zero) | B17: =B16-BP!$C$39 -> 0 | C17: =C16-BP!$C$40 -> 0 | D17: =D16-BP!$C$41 -> 0 | E17: =E16-BP!$C$42 -> 0 | F17: =SUM(B17:E17) -> 0

Sheet RWA
A1: RWA, Patrimônio de Referência e Índice de Basileia
A2: Em R$ mil | FPR ilustrativos (aba Dados) | exigência do S4: 10,5% do RWA
A4: Exposição | B4: FPR | C4: Exposição 2024 | D4: RWA 2024 | E4: Exposição 2025 | F4: RWA 2025
A5: Disponibilidades | B5: =Dados!$B$88 -> 0 | C5: =BP!$B$6 -> 28000 | D5: =C5*$B5 -> 0 | E5: =BP!$C$6 -> 31000 | F5: =E5*$B5 -> 0
A6: Centralização financeira | B6: =Dados!$B$89 -> 0.2 | C6: =BP!$B$7 -> 695540 | D6: =C6*$B6 -> 139108 | E6: =BP!$C$7 -> 789080 | F6: =E6*$B6 -> 157816
A7: Aplicações interfinanceiras | B7: =Dados!$B$90 -> 0.2 | C7: =BP!$B$8 -> 60000 | D7: =C7*$B7 -> 12000 | E7: =BP!$C$8 -> 85000 | F7: =E7*$B7 -> 17000
A8: Títulos públicos federais | B8: =Dados!$B$91 -> 0 | C8: =BP!$B$9 -> 140000 | D8: =C8*$B8 -> 0 | E8: =BP!$C$9 -> 150000 | F8: =E8*$B8 -> 0
A9: Carteira comercial (líquida de provisão) | B9: =Dados!$B$92 -> 0.85 | C9: =BP!$B$10+BP!$B$11-Dados!$C$48 -> 1050000 | D9: =C9*$B9 -> 892500 | E9: =BP!$C$10+BP!$C$11-Dados!$D$48 -> 1188000 | F9: =E9*$B9 -> 1009800
A10: Carteira rural (líquida de provisão) | B10: =Dados!$B$93 -> 0.75 | C10: =BP!$B$12-Dados!$C$49 -> 508000 | D10: =C10*$B10 -> 381000 | E10: =BP!$C$12-Dados!$D$49 -> 574000 | F10: =E10*$B10 -> 430500
A11: Outros ativos financeiros | B11: =Dados!$B$94 -> 1 | C11: =BP!$B$16 -> 45000 | D11: =C11*$B11 -> 45000 | E11: =BP!$C$16 -> 52000 | F11: =E11*$B11 -> 52000
A12: Ativos fiscais | B12: =Dados!$B$95 -> 1 | C12: =BP!$B$17 -> 9000 | D12: =C12*$B12 -> 9000 | E12: =BP!$C$17 -> 12000 | F12: =E12*$B12 -> 12000
A13: BNDU e outros ativos | B13: =Dados!$B$96 -> 1 | C13: =BP!$B$18+BP!$B$19 -> 21000 | D13: =C13*$B13 -> 21000 | E13: =BP!$C$18+BP!$C$19 -> 26000 | F13: =E13*$B13 -> 26000
A14: Investimentos | B14: =Dados!$B$97 -> 1 | C14: =BP!$B$20 -> 95000 | D14: =C14*$B14 -> 95000 | E14: =BP!$C$20 -> 104000 | F14: =E14*$B14 -> 104000
A15: Imobilizado | B15: =Dados!$B$98 -> 1 | C15: =BP!$B$21 -> 62000 | D15: =C15*$B15 -> 62000 | E15: =BP!$C$21 -> 70000 | F15: =E15*$B15 -> 70000
A16: Coobrigações e garantias (fora do balanço) | B16: =Dados!$B$99 -> 0.75 | C16: =BP!$B$47 -> 180000 | D16: =C16*$B16 -> 135000 | E16: =BP!$C$47 -> 210000 | F16: =E16*$B16 -> 157500
A18: RWA de risco de crédito (soma) | D18: =SUM(D5:D16) -> 1791608 | F18: =SUM(F5:F16) -> 2036616
A19: Receita bruta média de 3 anos | D19: =AVERAGE(Dados!$B$76,Dados!$B$77,Dados!$C$75) -> 195566.67 | F19: =AVERAGE(Dados!$B$77,Dados!$C$75,Dados!$D$75) -> 231166.67
A20: RWA de risco operacional = fator × receita média ÷ F | D20: =Dados!$B$78*D19/Dados!$B$79 -> 366687.5 | F20: =Dados!$B$78*F19/Dados!$B$79 -> 433437.5
A21: RWA de risco de mercado | D21: =Dados!$C$73 -> 3000 | F21: =Dados!$D$73 -> 4000
A22: RWA TOTAL | D22: =D18+D20+D21 -> 2161295.5 | F22: =F18+F20+F21 -> 2474053.5
A23: Densidade: RWA ÷ ativo total | D23: =D22/BP!$B$23 -> 0.79531322 | F23: =F22/BP!$C$23 -> 0.80168158
A24: Patrimônio líquido | D24: =BP!$B$43 -> 305540 | F24: =BP!$C$43 -> 349080
A25: (-) Ajustes prudenciais (intangível + outros) | D25: =-(BP!$B$22+Dados!$C$74) -> -7000 | F25: =-(BP!$C$22+Dados!$D$74) -> -8000
A26: (=) Capital principal (Nível I) | D26: =D24+D25 -> 298540 | F26: =F24+F25 -> 341080
A27: (+) Nível II: LFS | D27: =BP!$B$32 -> 0 | F27: =BP!$C$32 -> 15000
A28: (=) PATRIMÔNIO DE REFERÊNCIA (PR) | D28: =D26+D27 -> 298540 | F28: =F26+F27 -> 356080
A29: Índice de Basileia = PR ÷ RWA | D29: =D28/D22 -> 0.13813012 | F29: =F28/F22 -> 0.14392575
A30: Índice de capital principal = CP ÷ RWA | D30: =D26/D22 -> 0.13813012 | F30: =F26/F22 -> 0.13786282
A31: MM/RWA = (Basileia - 10,5%) em p.p. | D31: =(D29-Dados!$B$80)*100 -> 3.3130117 | F31: =(F29-Dados!$B$80)*100 -> 3.8925748
A32: Margem de capital (R$ mil) = PR - 10,5% × RWA | D32: =D28-Dados!$B$80*D22 -> 71603.973 | F32: =F28-Dados!$B$80*F22 -> 96304.383
A33: Potencial de crédito até MM/RWA de 2 p.p. = (PR ÷ 12,5% - RWA) ÷ 1,1 | D33: =(D28/(Dados!$B$80+Dados!$B$81)-D22)/Dados!$B$82 -> 206385.91 | F33: =(F28/(Dados!$B$80+Dados!$B$81)-F22)/Dados!$B$82 -> 340533.18
A34: Índice de Basileia sem a LFS | D34: =D26/D22 -> 0.13813012 | F34: =F26/F22 -> 0.13786282

Sheet Indicadores
A1: Os 15 indicadores calculados (2024 e 2025)
A2: Cada linha é uma fórmula viva. Coluna E: variação (p.p. para taxas, % para valores).
A4: Indicador | B4: Como se calcula | C4: 2024 | D4: 2025 | E4: Variação | F4: O que olhar
A5: 1. PATRIMÔNIO LÍQUIDO (PL)
A6: Patrimônio líquido (R$ mil) | B6: Capital social + reservas + sobras + ajustes | C6: =BP!$B$43 -> 305540 | D6: =BP!$C$43 -> 349080 | E6: =IFERROR(D6/C6-1,"n.a.") -> 0.1425018 | F6: Colchão para perdas e base para crescer
A7: Crescimento do PL | B7: PL do ano ÷ PL do ano anterior - 1 | C7: =Dados!$C$29/Dados!$B$29-1 -> 0.091214286 | D7: =Dados!$D$29/Dados!$C$29-1 -> 0.1425018 | E7: =(D7-C7)*100 -> 5.1287514 | F7: Compare com o crescimento do RWA
A8: PL ÷ ativo total | B8: PL ÷ ativo | C8: =BP!$B$43/BP!$B$23 -> 0.11243257 | D8: =BP!$C$43/BP!$C$23 -> 0.11311437 | E8: =(D8-C8)*100 -> 0.068180394 | F8: Alavancagem contábil (sem risco)
A9: Ativo ÷ PL (vezes) | B9: Ativo ÷ PL | C9: =BP!$B$23/BP!$B$43 -> 8.8942201 | D9: =BP!$C$23/BP!$C$43 -> 8.8406096 | E9: =D9-C9 -> -0.053610467 | F9: Quantos reais de ativo por real de capital
A10: Capital social ÷ PL | B10: Quotas ÷ PL | C10: =BP!$B$39/BP!$B$43 -> 0.42547621 | D10: =BP!$C$39/BP!$C$43 -> 0.45797525 | E10: =(D10-C10)*100 -> 3.2499043 | F10: Quanto do PL pode sair com resgate de quotas
A11: Capital social por associado (R$) | B11: Capital × 1.000 ÷ associados | C11: =BP!$B$39*1000/Dados!$C$58 -> 1326.5306 | D11: =BP!$C$39*1000/Dados!$D$58 -> 1508.2075 | E11: =IFERROR(D11/C11-1,"n.a.") -> 0.13695646
A12: 2. CRESCIMENTO DA CARTEIRA DE CRÉDITO
A13: Carteira bruta (R$ mil) | B13: Empréstimos + financiamentos + rural | C13: =BP!$B$13 -> 1640000 | D13: =BP!$C$13 -> 1870000 | E13: =IFERROR(D13/C13-1,"n.a.") -> 0.1402439
A14: Crescimento nominal da carteira | B14: Carteira ÷ carteira anterior - 1 | C14: =Dados!$C$18/Dados!$B$18-1 -> 0.13103448 | D14: =Dados!$D$18/Dados!$C$18-1 -> 0.1402439 | E14: =(D14-C14)*100 -> 0.92094197 | F14: Acima do PL consome capital
A15: Crescimento real (descontado o IPCA) | B15: (1 + nominal) ÷ (1 + IPCA) - 1 | C15: =(1+C14)/(1+Dados!$C$6)-1 -> 0.079231377 | D15: =(1+D14)/(1+Dados!$D$6)-1 -> 0.09114249 | E15: =(D15-C15)*100 -> 1.1911114 | F15: Crescimento de verdade
A16: Crescimento da carteira comercial | C16: =Dados!$C$16/Dados!$B$16-1 -> 0.13131313 | D16: =Dados!$D$16/Dados!$C$16-1 -> 0.14285714 | E16: =(D16-C16)*100 -> 1.1544012
A17: Crescimento da carteira rural | C17: =Dados!$C$17/Dados!$B$17-1 -> 0.13043478 | D17: =Dados!$D$17/Dados!$C$17-1 -> 0.13461538 | E17: =(D17-C17)*100 -> 0.4180602
A18: Crescimento do ativo | C18: =Dados!$C$9/Dados!$B$9-1 -> 0.13704603 | D18: =Dados!$D$9/Dados!$C$9-1 -> 0.1356153 | E18: =(D18-C18)*100 -> -0.1430726
A19: 3. CAPTAÇÃO (DEPÓSITOS À VISTA, POUPANÇA, RDC E LCA)
A20: Captação com associados (R$ mil) | B20: Depósitos + LCA | C20: =Dados!$C$25 -> 2050000 | D20: =Dados!$D$25 -> 2315000 | E20: =IFERROR(D20/C20-1,"n.a.") -> 0.12926829
A21: Crescimento da captação | C21: =Dados!$C$25/Dados!$B$25-1 -> 0.14206128 | D21: =Dados!$D$25/Dados!$C$25-1 -> 0.12926829 | E21: =(D21-C21)*100 -> -1.2792989 | F21: Se cresce menos que o crédito, a liquidez cai
A22: Mix: depósito à vista | B22: DV ÷ captação | C22: =BP!$B$25/Dados!$C$25 -> 0.1902439 | D22: =BP!$C$25/Dados!$D$25 -> 0.17710583 | E22: =(D22-C22)*100 -> -1.3138071 | F22: Funding mais barato
A23: Mix: poupança | C23: =BP!$B$26/Dados!$C$25 -> 0.10243902 | D23: =BP!$C$26/Dados!$D$25 -> 0.10151188 | E23: =(D23-C23)*100 -> -0.092714534
A24: Mix: RDC | C24: =BP!$B$27/Dados!$C$25 -> 0.64878049 | D24: =BP!$C$27/Dados!$D$25 -> 0.65658747 | E24: =(D24-C24)*100 -> 0.78069852 | F24: Funding mais caro e mais estável
A25: Mix: LCA | C25: =BP!$B$29/Dados!$C$25 -> 0.058536585 | D25: =BP!$C$29/Dados!$D$25 -> 0.064794816 | E25: =(D25-C25)*100 -> 0.6258231
A26: Custo médio da captação (inclui DV a custo zero) | B26: -(poupança + RDC + LCA) da DSP ÷ captação média | C26: =-(DSP!$B$13+DSP!$B$14+DSP!$B$15)/AVERAGE(Dados!$B$25,Dados!$C$25) -> 0.085149545 | D26: =-(DSP!$C$13+DSP!$C$14+DSP!$C$15)/AVERAGE(Dados!$C$25,Dados!$D$25) -> 0.11097365 | E26: =(D26-C26)*100 -> 2.5824109
A27: Custo do RDC em % do CDI | B27: -(despesa RDC) ÷ RDC médio ÷ CDI | C27: =-DSP!$B$14/AVERAGE(Dados!$B$22,Dados!$C$22)/Dados!$C$5 -> 1.0180527 | D27: =-DSP!$C$14/AVERAGE(Dados!$C$22,Dados!$D$22)/Dados!$D$5 -> 1.0104282 | E27: =(D27-C27)*100 -> -0.762451 | F27: Acima de 100% sem crédito bem precificado destrói margem
A28: Crédito ÷ captação | B28: Carteira ÷ (depósitos + LCA) | C28: =BP!$B$13/Dados!$C$25 -> 0.8 | D28: =BP!$C$13/Dados!$D$25 -> 0.80777538 | E28: =(D28-C28)*100 -> 0.7775378 | F28: Quanto da captação virou crédito
A29: 4. MARGEM FINANCEIRA
A30: Margem financeira (R$ mil) | B30: Crédito + liquidez - captação - repasses | C30: =Gerencial!$B$9 -> 193200 | D30: =Gerencial!$C$9 -> 204800 | E30: =IFERROR(D30/C30-1,"n.a.") -> 0.060041408
A31: Margem financeira ÷ ativo médio (NIM) | B31: Margem ÷ média do ativo | C31: =Gerencial!$B$9/AVERAGE(Dados!$B$9,Dados!$C$9) -> 0.075652858 | D31: =Gerencial!$C$9/AVERAGE(Dados!$C$9,Dados!$D$9) -> 0.07057664 | E31: =(D31-C31)*100 -> -0.50762182 | F31: Compare sempre com o CDI do período
A32: Taxa média da carteira | B32: Receita de crédito ÷ carteira média | C32: =DSP!$B$6/AVERAGE(Dados!$B$18,Dados!$C$18) -> 0.18828479 | D32: =DSP!$C$6/AVERAGE(Dados!$C$18,Dados!$D$18) -> 0.19680912 | E32: =(D32-C32)*100 -> 0.85243272
A33: Taxa média da liquidez | B33: Receita da liquidez ÷ liquidez rentável média | C33: =Gerencial!$B$6/AVERAGE(Dados!$B$14,Dados!$C$14) -> 0.1092909 | D33: =Gerencial!$C$6/AVERAGE(Dados!$C$14,Dados!$D$14) -> 0.14336171 | E33: =(D33-C33)*100 -> 3.4070808 | F33: Perto de 100% do CDI
A34: 5. SPREAD FINANCEIRO
A35: Spread de crédito (p.p.) | B35: Taxa da carteira - custo da captação | C35: =(C32-C26)*100 -> 10.313524 | D35: =(D32-D26)*100 -> 8.5835463 | E35: =D35-C35 -> -1.7299782
A36: Taxa da carteira - CDI (p.p.) | B36: Prêmio da carteira sobre o CDI | C36: =(C32-Dados!$C$5)*100 -> 7.928479 | D36: =(D32-Dados!$D$5)*100 -> 5.3809117 | E36: =D36-C36 -> -2.5475673 | F36: Carteira pré perde prêmio quando o CDI sobe
A37: 6. ROE E RESULTADO RECORRENTE
A38: Resultado antes dos juros ao capital (R$ mil) | B38: DSP | C38: =DSP!$B$39 -> 58500 | D38: =DSP!$C$39 -> 53700 | E38: =IFERROR(D38/C38-1,"n.a.") -> -0.082051282
A39: PL médio (R$ mil) | B39: Média do PL inicial e final | C39: =AVERAGE(Dados!$B$29,Dados!$C$29) -> 292770 | D39: =AVERAGE(Dados!$C$29,Dados!$D$29) -> 327310 | E39: =IFERROR(D39/C39-1,"n.a.") -> 0.11797657
A40: ROE | B40: Resultado ÷ PL médio | C40: =C38/C39 -> 0.19981555 | D40: =D38/D39 -> 0.16406465 | E40: =(D40-C40)*100 -> -3.5750907 | F40: Compare com o custo de capital (~15%) e com o CDI
A41: ROA | B41: Resultado ÷ ativo médio | C41: =C38/AVERAGE(Dados!$B$9,Dados!$C$9) -> 0.02290731 | D41: =D38/AVERAGE(Dados!$C$9,Dados!$D$9) -> 0.018505691 | E41: =(D41-C41)*100 -> -0.44016183
A42: DuPont: margem (resultado ÷ receita líquida) | C42: =C38/Gerencial!$B$12 -> 0.2480916 | D42: =D38/Gerencial!$C$12 -> 0.20878694 | E42: =(D42-C42)*100 -> -3.9304667
A43: DuPont: giro (receita líquida ÷ ativo médio) | C43: =Gerencial!$B$12/AVERAGE(Dados!$B$9,Dados!$C$9) -> 0.092334079 | D43: =Gerencial!$C$12/AVERAGE(Dados!$C$9,Dados!$D$9) -> 0.088634335 | E43: =(D43-C43)*100 -> -0.36997435
A44: DuPont: alavancagem (ativo médio ÷ PL médio) | C44: =AVERAGE(Dados!$B$9,Dados!$C$9)/C39 -> 8.7227858 | D44: =AVERAGE(Dados!$C$9,Dados!$D$9)/D39 -> 8.865632 | E44: =D44-C44 -> 0.14284617
A45: Itens não recorrentes (R$ mil) | B45: Notas | C45: =Dados!$C$66 -> -2200 | D45: =Dados!$D$66 -> 9200 | E45: =IFERROR(D45/C45-1,"n.a.") -> -5.1818182
A46: Resultado recorrente (R$ mil) | B46: Resultado - não recorrentes | C46: =Gerencial!$B$21 -> 60700 | D46: =Gerencial!$C$21 -> 44500 | E46: =IFERROR(D46/C46-1,"n.a.") -> -0.26688633
A47: ROE recorrente | B47: Resultado recorrente ÷ PL médio | C47: =C46/C39 -> 0.20732999 | D47: =D46/D39 -> 0.13595674 | E47: =(D47-C47)*100 -> -7.1373248 | F47: O que se repete no ano que vem
A48: 7. EFICIÊNCIA OPERACIONAL (COST-TO-INCOME)
A49: Índice de eficiência (IE) | B49: -Despesas administrativas ÷ receita líquida | C49: =-Gerencial!$B$13/Gerencial!$B$12 -> 0.58524173 | D49: =-Gerencial!$C$13/Gerencial!$C$12 -> 0.59097978 | E49: =(D49-C49)*100 -> 0.5738052 | F49: Menor é melhor
A50: IE recorrente | B50: Sem PDV na despesa e sem reversão de contingência na receita | C50: =-(Gerencial!$B$13-Dados!$C$62)/(Gerencial!$B$12-Dados!$C$64) -> 0.57463953 | D50: =-(Gerencial!$C$13-Dados!$D$62)/(Gerencial!$C$12-Dados!$D$64) -> 0.59795437 | E50: =(D50-C50)*100 -> 2.3314842
A51: IE ajustado ao risco (IEAR) | B51: -(Desp. adm + PDD líquida) ÷ receita líquida | C51: =-(Gerencial!$B$13+Gerencial!$B$14)/Gerencial!$B$12 -> 0.75063613 | D51: =-(Gerencial!$C$13+Gerencial!$C$14)/Gerencial!$C$12 -> 0.80482115 | E51: =(D51-C51)*100 -> 5.4185019 | F51: Acima de 100% = prejuízo
A52: 8. INADIMPLÊNCIA
A53: Inadimplência acima de 90 dias (NPL 90) | B53: Vencidos > 90 dias ÷ carteira | C53: =Dados!$C$38/BP!$B$13 -> 0.018902439 | D53: =Dados!$D$38/BP!$C$13 -> 0.029411765 | E53: =(D53-C53)*100 -> 1.0509326 | F53: Atraso que já virou problema
A54: Inadimplência de 15 a 90 dias | B54: (15-30 + 31-60 + 61-90) ÷ carteira | C54: =(Dados!$C$35+Dados!$C$36+Dados!$C$37)/BP!$B$13 -> 0.02195122 | D54: =(Dados!$D$35+Dados!$D$36+Dados!$D$37)/BP!$C$13 -> 0.026737968 | E54: =(D54-C54)*100 -> 0.47867484 | F54: Sinal antecedente do NPL 90
A55: Estágio 3 ÷ carteira | B55: Ativos problemáticos | C55: =Dados!$C$44/BP!$B$13 -> 0.035365854 | D55: =Dados!$D$44/BP!$C$13 -> 0.042780749 | E55: =(D55-C55)*100 -> 0.7414895 | F55: Inclui reestruturados, por isso maior que o NPL 90
A56: Renegociadas ÷ carteira | C56: =Dados!$C$50/BP!$B$13 -> 0.025 | D56: =Dados!$D$50/BP!$C$13 -> 0.03315508 | E56: =(D56-C56)*100 -> 0.81550802 | F56: Renegociação alta pode esconder atraso
A57: 9. PDD / PROVISÃO PARA PERDAS
A58: Provisão ÷ carteira | B58: -Provisão ÷ carteira | C58: =-BP!$B$14/BP!$B$13 -> 0.05 | D58: =-BP!$C$14/BP!$C$13 -> 0.057754011 | E58: =(D58-C58)*100 -> 0.77540107
A59: Cobertura do NPL 90 | B59: -Provisão ÷ vencidos > 90 dias | C59: =-BP!$B$14/Dados!$C$38 -> 2.6451613 | D59: =-BP!$C$14/Dados!$D$38 -> 1.9636364 | E59: =(D59-C59)*100 -> -68.152493 | F59: Abaixo de 100%: provisão não cobre nem o atraso
A60: Cobertura do estágio 3 | B60: Provisão do E3 ÷ saldo do E3 | C60: =Dados!$C$47/Dados!$C$44 -> 0.80810345 | D60: =Dados!$D$47/Dados!$D$44 -> 0.797 | E60: =(D60-C60)*100 -> -1.1103448
A61: Custo do risco (PDD ÷ carteira média) | B61: -PDD ÷ carteira média | C61: =-DSP!$B$22/AVERAGE(Dados!$B$18,Dados!$C$18) -> 0.029773463 | D61: =-DSP!$C$22/AVERAGE(Dados!$C$18,Dados!$D$18) -> 0.036467236 | E61: =(D61-C61)*100 -> 0.66937737 | F61: Compare com o prêmio da carteira sobre o CDI
A62: Custo do risco líquido de recuperações | B62: -(PDD + recuperação) ÷ carteira média | C62: =-Gerencial!$B$14/AVERAGE(Dados!$B$18,Dados!$C$18) -> 0.025242718 | D62: =-Gerencial!$C$14/AVERAGE(Dados!$C$18,Dados!$D$18) -> 0.031339031 | E62: =(D62-C62)*100 -> 0.60963129
A63: Baixas para prejuízo (R$ mil) | B63: Provisão inicial + PDD - provisão final (em módulo) | C63: =-(Dados!$B$19+DSP!$B$22-Dados!$C$19) -> 32000 | D63: =-(Dados!$C$19+DSP!$C$22-Dados!$D$19) -> 38000 | E63: =IFERROR(D63/C63-1,"n.a.") -> 0.1875
A64: 10. RWA (ATIVOS PONDERADOS PELO RISCO)
A65: RWA total (R$ mil) | B65: Crédito + operacional + mercado | C65: =RWA!$D$22 -> 2161295.5 | D65: =RWA!$F$22 -> 2474053.5 | E65: =IFERROR(D65/C65-1,"n.a.") -> 0.14470858
A66: RWA de crédito (R$ mil) | B66: Soma de exposição × FPR | C66: =RWA!$D$18 -> 1791608 | D66: =RWA!$F$18 -> 2036616 | E66: =IFERROR(D66/C66-1,"n.a.") -> 0.13675313
A67: RWA operacional (R$ mil) | B67: 15% × receita média ÷ 8% | C67: =RWA!$D$20 -> 366687.5 | D67: =RWA!$F$20 -> 433437.5 | E67: =IFERROR(D67/C67-1,"n.a.") -> 0.18203511
A68: Densidade (RWA ÷ ativo) | C68: =RWA!$D$23 -> 0.79531322 | D68: =RWA!$F$23 -> 0.80168158 | E68: =(D68-C68)*100 -> 0.63683586 | F68: Quanto risco cada real de ativo carrega
A69: 11. ÍNDICE DE BASILEIA
A70: Patrimônio de Referência (R$ mil) | B70: Capital principal + Nível II | C70: =RWA!$D$28 -> 298540 | D70: =RWA!$F$28 -> 356080 | E70: =IFERROR(D70/C70-1,"n.a.") -> 0.19273799
A71: Índice de Basileia | B71: PR ÷ RWA | C71: =RWA!$D$29 -> 0.13813012 | D71: =RWA!$F$29 -> 0.14392575 | E71: =(D71-C71)*100 -> 0.57956309 | F71: Mínimo do S4: 10,5%
A72: MM/RWA (folga em p.p.) | B72: Basileia - 10,5% | C72: =RWA!$D$31 -> 3.3130117 | D72: =RWA!$F$31 -> 3.8925748 | E72: =D72-C72 -> 0.57956309 | F72: Política de recursos corporativos: piso de 2 p.p.
A73: Potencial de crédito até o piso (R$ mil) | B73: (PR ÷ 12,5% - RWA) ÷ 1,1 | C73: =RWA!$D$33 -> 206385.91 | D73: =RWA!$F$33 -> 340533.18 | E73: =IFERROR(D73/C73-1,"n.a.") -> 0.64998271
A74: 12. LIQUIDEZ (LCR E INDICADORES INTERNOS)
A75: Liquidez total (R$ mil) | B75: Caixa + centralização + aplicações + TVM | C75: =Dados!$C$15 -> 923540 | D75: =Dados!$D$15 -> 1055080 | E75: =IFERROR(D75/C75-1,"n.a.") -> 0.14243021
A76: Liquidez ÷ ativo | C76: =Dados!$C$15/BP!$B$23 -> 0.33984412 | D76: =Dados!$D$15/BP!$C$23 -> 0.34188355 | E76: =(D76-C76)*100 -> 0.20394308
A77: Índice de liquidez interno | B77: Liquidez ÷ (NML × depósitos) | C77: =Dados!$C$15/(Dados!$B$83*BP!$B$28) -> 1.5950604 | D77: =Dados!$D$15/(Dados!$B$83*BP!$C$28) -> 1.6244496 | E77: =D77-C77 -> 0.029389128 | F77: Abaixo de 1 falta; muito acima custa
A78: Liquidez imediata | B78: (Caixa + centralização) ÷ depósitos à vista | C78: =(BP!$B$6+BP!$B$7)/BP!$B$25 -> 1.8552308 | D78: =(BP!$C$6+BP!$C$7)/BP!$C$25 -> 2.0001951 | E78: =D78-C78 -> 0.14496435
A79: LCR: ativos líquidos (R$ mil) | B79: Caixa + TVM + centralização | C79: =BP!$B$6+BP!$B$9+BP!$B$7 -> 863540 | D79: =BP!$C$6+BP!$C$9+BP!$C$7 -> 970080 | E79: =IFERROR(D79/C79-1,"n.a.") -> 0.12337587
A80: LCR: saídas em 30 dias de estresse (R$ mil) | B80: Saldos × fatores + vencimentos | C80: =BP!$B$25*Dados!$C$118+BP!$B$26*Dados!$C$119+BP!$B$27*Dados!$C$120+Dados!$C$121+Dados!$C$122+Dados!$C$123*Dados!$C$124+Dados!$C$125 -> 296100 | D80: =BP!$C$25*Dados!$D$118+BP!$C$26*Dados!$D$119+BP!$C$27*Dados!$D$120+Dados!$D$121+Dados!$D$122+Dados!$D$123*Dados!$D$124+Dados!$D$125 -> 330400 | E80: =IFERROR(D80/C80-1,"n.a.") -> 0.11583924
A81: LCR: entradas consideradas (R$ mil) | B81: Mínimo(entradas; 75% das saídas) | C81: =MIN(Dados!$C$126*Dados!$C$127+Dados!$C$128,Dados!$B$129*C80) -> 92500 | D81: =MIN(Dados!$D$126*Dados!$D$127+Dados!$D$128,Dados!$B$129*D80) -> 105000 | E81: =IFERROR(D81/C81-1,"n.a.") -> 0.13513514
A82: LCR didático | B82: Ativos líquidos ÷ (saídas - entradas) | C82: =C79/(C80-C81) -> 4.2413556 | D82: =D79/(D80-D81) -> 4.3038154 | E82: =(D82-C82)*100 -> 6.245984 | F82: Regulatório só no S1; aqui é régua interna
A83: 13. FTP (FUNDS TRANSFER PRICING): MARGEM POR PRODUTO (R$ mil)
A84: Crédito comercial: receita - saldo médio × FTP | C84: =Dados!$C$54-AVERAGE(Dados!$B$16,Dados!$C$16)*Dados!$C$102 -> 109720 | D84: =Dados!$D$54-AVERAGE(Dados!$C$16,Dados!$D$16)*Dados!$D$102 -> 96000 | E84: =IFERROR(D84/C84-1,"n.a.") -> -0.12504557
A85: Crédito rural: receita - saldo médio × FTP | C85: =Dados!$C$55-AVERAGE(Dados!$B$17,Dados!$C$17)*Dados!$C$103 -> 14700 | D85: =Dados!$D$55-AVERAGE(Dados!$C$17,Dados!$D$17)*Dados!$D$103 -> 9460 | E85: =IFERROR(D85/C85-1,"n.a.") -> -0.35646259
A86: Depósito à vista: saldo médio × FTP - custo (zero) | C86: =AVERAGE(Dados!$B$20,Dados!$C$20)*Dados!$C$104 -> 36750 | D86: =AVERAGE(Dados!$C$20,Dados!$D$20)*Dados!$D$104 -> 51600 | E86: =IFERROR(D86/C86-1,"n.a.") -> 0.40408163
A87: Poupança: saldo médio × FTP - despesa | C87: =AVERAGE(Dados!$B$21,Dados!$C$21)*Dados!$C$105+DSP!$B$13 -> 3600 | D87: =AVERAGE(Dados!$C$21,Dados!$D$21)*Dados!$D$105+DSP!$C$13 -> 8200 | E87: =IFERROR(D87/C87-1,"n.a.") -> 1.2777778
A88: RDC: saldo médio × FTP - despesa | C88: =AVERAGE(Dados!$B$22,Dados!$C$22)*Dados!$C$106+DSP!$B$14 -> -2440 | D88: =AVERAGE(Dados!$C$22,Dados!$D$22)*Dados!$D$106+DSP!$C$14 -> -2125 | E88: =IFERROR(D88/C88-1,"n.a.") -> -0.12909836
A89: LCA: saldo médio × FTP - despesa | C89: =AVERAGE(Dados!$B$24,Dados!$C$24)*Dados!$C$107+DSP!$B$15 -> 280 | D89: =AVERAGE(Dados!$C$24,Dados!$D$24)*Dados!$D$107+DSP!$C$15 -> 560 | E89: =IFERROR(D89/C89-1,"n.a.") -> 1
A90: Tesouraria/ALM: o que sobra para fechar a margem | B90: Margem financeira - soma dos produtos | C90: =Gerencial!$B$9-SUM(C84:C89) -> 30590 | D90: =Gerencial!$C$9-SUM(D84:D89) -> 41105 | E90: =IFERROR(D90/C90-1,"n.a.") -> 0.34373978 | F90: Inclui o ganho de financiar ativos com PL e o descasamento
A91: CONFERÊNCIAS
A92: BP fecha? (ativo - passivo - PL) | C92: =BP!$B$45 -> 0 | D92: =BP!$C$45 -> 0 | F92: Deve ser zero
A93: DSP bate com a visão gerencial? | C93: =Gerencial!$B$19 -> 0 | D93: =Gerencial!$C$19 -> 0 | F93: Deve ser zero
A95: 14. RAROC POR CARTEIRA EM 2025 (R$ mil)
A96: Componente | B96: Como se calcula | C96: Comercial | D96: Rural
A97: Saldo médio | B97: Média da carteira | C97: =AVERAGE(Dados!$C$16,Dados!$D$16) -> 1200000 | D97: =AVERAGE(Dados!$C$17,Dados!$D$17) -> 555000
A98: Provisão média | C98: =AVERAGE(Dados!$C$48,Dados!$D$48) -> 81000 | D98: =AVERAGE(Dados!$C$49,Dados!$D$49) -> 14000
A99: Margem após FTP | B99: Linha de FTP acima | C99: =D84 -> 96000 | D99: =D85 -> 9460
A100: (-) Custo operacional alocado | B100: Saldo médio × % de custo | C100: =C97*Dados!$B$110 -> 42000 | D100: =D97*Dados!$B$111 -> 8325
A101: (-) Perda esperada | B101: Saldo médio × % de PE | C101: =C97*Dados!$B$112 -> 45600 | D101: =D97*Dados!$B$113 -> 5550
A102: RWA da carteira | B102: (Saldo médio - provisão média) × FPR | C102: =(C97-C98)*Dados!$B$92 -> 951150 | D102: =(D97-D98)*Dados!$B$93 -> 405750
...

Sheet Ex01
A1: Exercício 01: Onde entra cada lançamento?
A2: Tema: linhas do BP
A3: Para cada evento, escolha a linha do balanço que ele afeta. A ideia é treinar o olhar: antes de analisar um número, saiba o que mora dentro dele.
A5: Nº | B5: Evento | C5: Linha do balanço (resposta) | D5: Por quê
A6: 1 | B6: Associado deposita R$ 5 mil em dinheiro na conta corrente. Qual linha do passivo aumenta? | C6: Depósitos à vista | D6: Dinheiro na conta corrente é depósito à vista: o associado saca quando quiser e a cooperativa não paga juros. No ativo, entra em Disponibilidades (caixa) e, no fim do dia, a sobra vai para a centralização.
A7: 2 | B7: A cooperativa libera R$ 200 mil de custeio agrícola para um produtor. Qual linha do ativo aumenta? | C7: Operações de crédito: financiamentos rurais | D7: Custeio, investimento e comercialização agrícola ficam em Financiamentos rurais e agroindustriais. O dinheiro sai da liquidez (centralização) e vira carteira.
A8: 3 | B8: A sobra de caixa do dia é transferida para a Cooperativa Central. Qual linha do ativo aumenta? | C8: Centralização financeira | D8: A sobra de recursos da singular fica aplicada na Central (relações interfinanceiras, centralização financeira), rendendo perto de 100% do CDI. É a principal reserva de liquidez.
A9: 4 | B9: Associado aplica R$ 50 mil em RDC. Qual linha do passivo aumenta? | C9: Depósitos a prazo (RDC) | D9: RDC (Recibo de Depósito Cooperativo) é o depósito a prazo da cooperativa, o equivalente ao CDB do banco. Paga um percentual do CDI e é garantido pelo FGCoop até o limite.
A10: 5 | B10: Associado compra R$ 30 mil em LCA emitida pela cooperativa. Qual linha do passivo aumenta? | C10: Recursos de aceites e emissão de títulos (LCA) | D10: LCA é um título emitido pela instituição com lastro em crédito do agronegócio. Fica em Recursos de aceites e emissão de títulos, não em depósitos.
A11: 6 | B11: A cooperativa recebe um trator em dação em pagamento de uma dívida vencida. Qual linha do ativo aumenta? | C11: Bens não de uso próprio (BNDU) | D11: Bem recebido para quitar dívida não é de uso da cooperativa: vai para BNDU até ser vendido. BNDU crescendo é sinal de recuperação de crédito difícil.
A12: 7 | B12: Um novo associado integraliza R$ 1 mil em quotas-partes. Qual linha aumenta? | C12: Capital social | D12: Quota-parte integralizada é capital social, dentro do patrimônio líquido. Ela pode ser devolvida quando o associado sai, por isso é um capital menos estável que as reservas.
A13: 8 | B13: A AGO destina 5% das sobras ao FATES. Em que linha do balanço o valor fica? | C13: Obrigações sociais e estatutárias | D13: Nas cooperativas de crédito, o FATES é registrado no passivo (obrigações sociais e estatutárias), e não no PL: é um recurso com destino obrigatório (assistência técnica, educacional e social).
A14: 9 | B14: Financiamento de máquina com recurso do BNDES repassado pelo Banco Sicredi. Qual linha do passivo aumenta? | C14: Obrigações por empréstimos e repasses | D14: O dinheiro veio de um repasse (BNDES, FINAME, BRDE) e a cooperativa deve devolvê-lo: Obrigações por empréstimos e repasses. No ativo, o financiamento entra na carteira de crédito.
A15: 10 | B15: A cooperativa subscreve quotas da Central e da Sicredi Participações. Qual linha do ativo aumenta? | C15: Investimentos | D15: Participação no capital de outras entidades do sistema é Investimento. Ela rende (juros ao capital, dividendos) mas não é liquidez.
A16: 11 | B16: A cooperativa presta fiança de R$ 100 mil a um associado perante um fornecedor. Onde aparece o valor garantido? | C16: Fora do balanço (coobrigações e garantias) | D16: Garantia prestada não sai do caixa: fica em contas de compensação (fora do balanço). Mesmo assim consome capital (entra no RWA) e, pela Res. 4.966, pode exigir provisão no passivo.
A17: 12 | B17: Compra de licença de software de uso por 5 anos. Qual linha do ativo aumenta? | C17: Intangível | D17: Software e licenças de longo prazo são ativos intangíveis, amortizados ao longo do uso. O intangível é deduzido do capital no cálculo do PR.
... A20: 15 | B20: Salários de dezembro, pagos só em janeiro. Qual linha do passivo aumenta no fechamento? | C20: Obrigações fiscais e outras obrigações | D20: Salários, encargos, tributos e fornecedores a pagar ficam em obrigações fiscais e outras obrigações. A contrapartida é despesa de pessoal.

Sheet Ex02
A1: Exercício 02: Análise vertical do passivo e do PL
A2: Tema: AV | valores em R$ mil, salvo indicação
A3: Use o BP da Coop Vale do Ipê. Calcule a participação de cada grupo no total do passivo + PL em 2024 e em 2025 e explique o que mudou na forma como a cooperativa se financia.
A4: Dica: AV = linha ÷ total do passivo + PL do mesmo ano. O total do passivo + PL é igual ao total do ativo.
A6: Item | B6: Passo / pergunta | C6: Resultado | D6: Unidade | E6: Fórmula (Excel PT-BR) | F6: Como foi feito
B7: Total do passivo + PL em 2024 | C7: =BP!$B$44 -> 2717540 | D7: R$ mil | E7: =BP!B44 | F7: Base da AV do lado direito do balanço (igual ao ativo total).
B8: Total do passivo + PL em 2025 | C8: =BP!$C$44 -> 3086080 | D8: R$ mil | E8: =BP!C44 | F8: Mesmo raciocínio para 2025.
A9: a | B9: RDC ÷ passivo + PL, 2024 | C9: =BP!$B$27/C7 -> 0.48941322 | D9: % | E9: =BP!B27/C7 | F9: Saldo de RDC de 2024 dividido pelo total.
A10: b | B10: RDC ÷ passivo + PL, 2025 | C10: =BP!$C$27/C8 -> 0.49253422 | D10: % | E10: =BP!C27/C8 | F10: Sobe: a cooperativa depende mais do funding que paga % do CDI.
A11: c | B11: Depósito à vista ÷ passivo + PL, 2024 | C11: =BP!$B$25/C7 -> 0.14351215 | D11: % | E11: =BP!B25/C7 | F11: Funding sem custo.
A12: d | B12: Depósito à vista ÷ passivo + PL, 2025 | C12: =BP!$C$25/C8 -> 0.13285462 | D12: % | E12: =BP!C25/C8 | F12: Cai: o associado tira dinheiro parado da conta quando o CDI está alto. A captação fica mais cara.
A13: e | B13: PL ÷ passivo + PL, 2025 | C13: =BP!$C$43/C8 -> 0.11311437 | D13: % | E13: =BP!C43/C8 | F13: Quanto do ativo é financiado com capital próprio (11,3%).
A14: f | B14: (Depósitos + LCA) ÷ passivo + PL, 2025 | C14: =(BP!$C$28+BP!$C$29)/C8 -> 0.75014258 | D14: % | E14: =(BP!C28+BP!C29)/C8 | F14: Três quartos do balanço vêm dos associados: é o modelo cooperativo.
A16: Leitura | B16: O mix piorou de custo: o RDC ganhou espaço e o depósito à vista perdeu. Com CDI alto, isso é esperado, mas pressiona a margem financeira. O PL manteve a participação, ou seja, cresceu no ritmo do balanço.

Sheet Ex03
A1: Exercício 03: Análise horizontal da DSP
A2: Tema: AH | valores em R$ mil, salvo indicação
A3: Calcule a variação de 2025 contra 2024 das linhas abaixo. Depois responda: por que a despesa de captação cresceu muito mais que a receita de crédito?
A4: Dica: AH = valor de 2025 ÷ valor de 2024 - 1. Despesas negativas dividem por negativas: o sinal some e a conta funciona.
A6: Item | B6: Passo / pergunta | C6: Resultado | D6: Unidade | E6: Fórmula (Excel PT-BR) | F6: Como foi feito
A7: a | B7: AH da receita de crédito | C7: =DSP!$C$6/DSP!$B$6-1 -> 0.1873496 | D7: % | E7: =DSP!C6/DSP!B6-1 | F7: 2025 ÷ 2024 - 1.
A8: b | B8: AH da despesa de captação | C8: =DSP!$C$18/DSP!$B$18-1 -> 0.48408408 | D8: % | E8: =DSP!C18/DSP!B18-1 | F8: Negativo ÷ negativo dá positivo: a fórmula funciona sem ABS.
A9: c | B9: AH da margem financeira | C9: =Gerencial!$C$9/Gerencial!$B$9-1 -> 0.060041408 | D9: % | E9: =Gerencial!C9/Gerencial!B9-1 | F9: Margem cresce bem menos que a carteira (14%).
A10: d | B10: AH da despesa de PDD | C10: =DSP!$C$22/DSP!$B$22-1 -> 0.39130435 | D10: % | E10: =DSP!C22/DSP!B22-1 | F10: PDD cresce quase 3 vezes mais que a carteira: piora de risco.
A11: e | B11: AH do resultado | C11: =DSP!$C$39/DSP!$B$39-1 -> -0.082051282 | D11: % | E11: =DSP!C39/DSP!B39-1 | F11: Resultado cai mesmo com a carteira crescendo.
A13: Por quê? | B13: A captação (RDC, LCA, poupança) é paga em % do CDI e reprecifica rápido: com o CDI médio subindo de 10,9% para 14,3%, a despesa explode. A carteira tem parte prefixada (comercial e rural) que só reprecifica no vencimento. A margem cresce pouco e a PDD maior come o resto.

Sheet Ex04
A1: Exercício 04: Margem financeira e NIM de 2024
A2: Tema: Margem financeira | valores em R$ mil, salvo indicação
A3: Monte a margem financeira de 2024 pela visão gerencial (receita de crédito + receita da liquidez - despesa de captação - despesa de repasses) e calcule o NIM sobre o ativo médio. Compare com 2025.
A4: Dica: Ativo médio de 2024 = (ativo de 31/12/2023 + ativo de 31/12/2024) ÷ 2. O ativo de 2023 está nas notas.
A6: Item | B6: Passo / pergunta | C6: Resultado | D6: Unidade | E6: Fórmula (Excel PT-BR) | F6: Como foi feito
A7: a | B7: Margem financeira de 2024 (R$ mil) | C7: =DSP!$B$6+DSP!$B$8+DSP!$B$9+DSP!$B$10+DSP!$B$18+DSP!$B$21 -> 193200 | D7: R$ mil | E7: =DSP!B6+DSP!B8+DSP!B9+DSP!B10+DSP!B18+DSP!B21 | F7: Receita de crédito + receita da liquidez + despesa de captação (negativa) + despesa de repasses (negativa).
B8: Ativo médio de 2024 | C8: =AVERAGE(Dados!$B$9,Dados!$C$9) -> 2553770 | D8: R$ mil | E8: =MÉDIA(Dados!B9;Dados!C9) | F8: Média do ativo de 31/12/2023 (notas) e de 31/12/2024.
A9: b | B9: NIM de 2024 | C9: =C7/C8 -> 0.075652858 | D9: % | E9: =C7/C8 | F9: Margem ÷ ativo médio.
B10: Ativo médio de 2025 | C10: =AVERAGE(Dados!$C$9,Dados!$D$9) -> 2901810 | D10: R$ mil | E10: =MÉDIA(Dados!C9;Dados!D9)
A11: c | B11: NIM de 2025 | C11: =Gerencial!$C$9/C10 -> 0.07057664 | D11: % | E11: =Gerencial!C9/C10 | F11: Mesma conta para 2025.
A12: d | B12: Variação do NIM (p.p.) | C12: =(C11-C9)*100 -> -0.50762182 | D12: p.p. | E12: =(C11-C9)*100 | F12: Queda de meio ponto: a margem cresceu menos que o ativo.
A14: Leitura | B14: O NIM caiu porque a captação ficou mais cara mais rápido que a carteira e porque a liquidez (que rende só o CDI) cresceu. Em reais a margem subiu: olhe sempre o percentual.

Sheet Ex05
A1: Exercício 05: Spread de 2024
A2: Tema: Spread | valores em R$ mil, salvo indicação
A3: Calcule as taxas médias implícitas de 2024 a partir da DSP e dos saldos médios. Use como captação os depósitos (à vista, poupança e RDC) e a LCA.
A4: Dica: Custo da captação = despesas de poupança + RDC + LCA (sem FGCoop e sem LFS) ÷ saldo médio de depósitos + LCA.
A6: Item | B6: Passo / pergunta | C6: Resultado | D6: Unidade | E6: Fórmula (Excel PT-BR) | F6: Como foi feito
B7: Carteira média de 2024 | C7: =AVERAGE(Dados!$B$18,Dados!$C$18) -> 1545000 | D7: R$ mil | E7: =MÉDIA(Dados!B18;Dados!C18) | F7: Média de 2023 e 2024.
A8: a | B8: Taxa média da carteira | C8: =DSP!$B$6/C7 -> 0.18828479 | D8: % | E8: =DSP!B6/C7 | F8: Receita de crédito ÷ carteira média.
B9: Captação média de 2024 (depósitos + LCA) | C9: =AVERAGE(Dados!$B$25,Dados!$C$25) -> 1922500 | D9: R$ mil | E9: =MÉDIA(Dados!B25;Dados!C25) | F9: Inclui o depósito à vista, que custa zero.
B10: Despesa de poupança + RDC + LCA | C10: =-(DSP!$B$13+DSP!$B$14+DSP!$B$15) -> 163700 | D10: R$ mil | E10: =-(DSP!B13+DSP!B14+DSP!B15) | F10: Sem FGCoop (não é juro) e sem LFS (é capital).
A11: b | B11: Custo médio da captação | C11: =C10/C9 -> 0.085149545 | D11: % | E11: =C10/C9 | F11: Despesa ÷ captação média.
A12: c | B12: Spread de crédito (p.p.) | C12: =(C8-C11)*100 -> 10.313524 | D12: p.p. | E12: =(C8-C11)*100 | F12: Diferença entre a taxa que recebe e a que paga.
A13: d | B13: Custo médio dos passivos onerosos | C13: =C10/(C9-AVERAGE(Dados!$B$20,Dados!$C$20)) -> 0.10578352 | D13: % | E13: =C10/(C9-MÉDIA(Dados!B20;Dados!C20)) | F13: Tira o depósito à vista do denominador: mostra o custo de quem cobra juros.
A15: Leitura | B15: Em 2024 o spread era de 10,3 p.p.; em 2025 cai para 8,6 p.p. O depósito à vista derruba o custo médio (8,5% contra 10,6% só dos onerosos): por isso perder DV dói.

Sheet Ex06
A1: Exercício 06: ROE contábil, ROE recorrente e DuPont de 2024
A2: Tema: ROE e resultado recorrente | valores em R$ mil, salvo indicação
A3: Calcule o ROE de 2024 (resultado antes dos juros ao capital ÷ PL médio), tire os itens não recorrentes listados nas notas e decomponha o ROE em margem × giro × alavancagem.
A4: Dica: Item não recorrente com sinal negativo (despesa) é somado de volta; com sinal positivo (ganho) é retirado.
A6: Item | B6: Passo / pergunta | C6: Resultado | D6: Unidade | E6: Fórmula (Excel PT-BR) | F6: Como foi feito
B7: Resultado de 2024 | C7: =DSP!$B$39 -> 58500 | D7: R$ mil | E7: =DSP!B39 | F7: Antes dos juros ao capital: é o que o capital do associado gerou.
B8: PL médio de 2024 | C8: =AVERAGE(Dados!$B$29,Dados!$C$29) -> 292770 | D8: R$ mil | E8: =MÉDIA(Dados!B29;Dados!C29) | F8: Média de 2023 (notas) e 2024.
A9: a | B9: ROE contábil | C9: =C7/C8 -> 0.19981555 | D9: % | E9: =C7/C8 | F9: Resultado ÷ PL médio.
B10: Itens não recorrentes de 2024 | C10: =Dados!$C$66 -> -2200 | D10: R$ mil | E10: =Dados!C66 | F10: PDV (-2.500) e venda de imóvel (+300): total -2.200.
A11: b | B11: Resultado recorrente | C11: =C7-C10 -> 60700 | D11: R$ mil | E11: =C7-C10 | F11: Tirar um item negativo significa somá-lo de volta.
A12: c | B12: ROE recorrente | C12: =C11/C8 -> 0.20732999 | D12: % | E12: =C11/C8 | F12: Resultado recorrente ÷ PL médio.
A13: d | B13: Margem (resultado ÷ receita líquida) | C13: =C7/Gerencial!$B$12 -> 0.2480916 | D13: % | E13: =C7/Gerencial!B12 | F13: Quanto de cada real de receita líquida vira resultado.
A14: e | B14: Giro (receita líquida ÷ ativo médio) | C14: =Gerencial!$B$12/AVERAGE(Dados!$B$9,Dados!$C$9) -> 0.092334079 | D14: % | E14: =Gerencial!B12/MÉDIA(Dados!B9;Dados!C9) | F14: Quanto de receita líquida cada real de ativo gera.
A15: f | B15: Alavancagem (ativo médio ÷ PL médio) | C15: =AVERAGE(Dados!$B$9,Dados!$C$9)/C8 -> 8.7227858 | D15: x | E15: =MÉDIA(Dados!B9;Dados!C9)/C8 | F15: Quantos reais de ativo cada real de PL sustenta.
B16: Prova: margem × giro × alavancagem | C16: =C13*C14*C15 -> 0.19981555 | D16: % | E16: =C13*C14*C15 | F16: Tem de dar o ROE do item a.
A18: Leitura | B18: Em 2024 o ROE recorrente (20,7%) era maior que o contábil: o PDV puxou o resultado para baixo. Em 2025 acontece o contrário (16,4% contábil e 13,6% recorrente). Comparar só o contábil esconde metade da piora.

Sheet Ex07
A1: Exercício 07: Eficiência operacional (cost-to-income)
A2: Tema: Eficiência | valores em R$ mil, salvo indicação
A3: Calcule o índice de eficiência (despesas administrativas ÷ receita líquida) e o IEAR (somando a PDD líquida de recuperações). Depois descubra quanto de despesa a cooperativa teria de cortar em 2025 para o IE recorrente voltar ao IE recorrente de 2024.
A4: Dica: Receita líquida = margem financeira + serviços e tarifas + outras receitas - outras despesas - tributárias +/- contingências.
A6: Item | B6: Passo / pergunta | C6: Resultado | D6: Unidade | E6: Fórmula (Excel PT-BR) | F6: Como foi feito
B7: Receita líquida de 2024 | C7: =Gerencial!$B$12 -> 235800 | D7: R$ mil | E7: =Gerencial!B12 | F7: Aba Gerencial.
A8: a | B8: IE de 2024 | C8: =-Gerencial!$B$13/C7 -> 0.58524173 | D8: % | E8: =-Gerencial!B13/C7 | F8: Despesas administrativas (pessoal + outras) ÷ receita líquida.
A9: b | B9: IEAR de 2024 | C9: =-(Gerencial!$B$13+Gerencial!$B$14)/C7 -> 0.75063613 | D9: % | E9: =-(Gerencial!B13+Gerencial!B14)/C7 | F9: Soma a PDD líquida de recuperações.
B10: Despesa adm recorrente de 2025 | C10: =-(Gerencial!$C$13-Dados!$D$62) -> 152000 | D10: R$ mil | E10: =-(Gerencial!C13-Dados!D62) | F10: Em 2025 não houve PDV: igual à despesa total.
B11: Receita líquida recorrente de 2025 | C11: =Gerencial!$C$12-Dados!$D$64 -> 254200 | D11: R$ mil | E11: =Gerencial!C12-Dados!D64 | F11: Tira a reversão de contingência de 3.000.
A12: c | B12: IE recorrente de 2025 | C12: =C10/C11 -> 0.59795437 | D12: % | E12: =C10/C11 | F12: Pior que o contábil (59,1%).
B13: IE recorrente de 2024 (meta) | C13: =-(Gerencial!$B$13-Dados!$C$62)/(Gerencial!$B$12-Dados!$C$64) -> 0.57463953 | D13: % | E13: =-(Gerencial!B13-Dados!C62)/(Gerencial!B12-Dados!C64) | F13: Sem o PDV de 2.500.
A14: d | B14: Corte necessário (R$ mil) | C14: =C10-C13*C11 -> 5926.6327 | D14: R$ mil | E14: =C10-C13*C11 | F14: Despesa atual - despesa que daria o IE meta com a mesma receita.
A16: Leitura | B16: O IE contábil quase não mexeu (58,5% para 59,1%), mas o recorrente piorou 2,3 p.p. E o IEAR subiu 5,4 p.p.: o maior problema de 2025 é o risco de crédito, não o custo.

Sheet Ex08
A1: Exercício 08: Inadimplência e provisão de 2024
A2: Tema: Inadimplência e PDD | valores em R$ mil, salvo indicação
A3: Use as notas de carteira por atraso e por estágio. Depois explique por que a cobertura caiu em 2025.
A4: Dica: Provisão final = provisão inicial + despesa de PDD - baixas. Isole as baixas.
A6: Item | B6: Passo / pergunta | C6: Resultado | D6: Unidade | E6: Fórmula (Excel PT-BR) | F6: Como foi feito
A7: a | B7: NPL 90 de 2024 | C7: =Dados!$C$38/BP!$B$13 -> 0.018902439 | D7: % | E7: =Dados!C38/BP!B13 | F7: Vencidos há mais de 90 dias ÷ carteira bruta.
A8: b | B8: Inadimplência 15 a 90 dias de 2024 | C8: =(Dados!$C$35+Dados!$C$36+Dados!$C$37)/BP!$B$13 -> 0.02195122 | D8: % | E8: =(Dados!C35+Dados!C36+Dados!C37)/BP!B13 | F8: Atraso curto que pode virar NPL nos próximos meses.
A9: c | B9: Cobertura do NPL 90 em 2024 | C9: =-BP!$B$14/Dados!$C$38 -> 2.6451613 | D9: % | E9: =-BP!B14/Dados!C38 | F9: Provisão (em módulo) ÷ vencidos > 90 dias.
A10: d | B10: Custo do risco de 2024 | C10: =-DSP!$B$22/AVERAGE(Dados!$B$18,Dados!$C$18) -> 0.029773463 | D10: % | E10: =-DSP!B22/MÉDIA(Dados!B18;Dados!C18) | F10: Despesa de PDD ÷ carteira média.
A11: e | B11: Baixas para prejuízo de 2024 | C11: =-(Dados!$B$19+DSP!$B$22-Dados!$C$19) -> 32000 | D11: R$ mil | E11: =-(Dados!B19+DSP!B22-Dados!C19) | F11: Provisão inicial (68.000) + PDD (46.000) - provisão final (82.000) = 32.000 baixados.
A12: f | B12: Estágio 3 ÷ carteira em 2025 | C12: =Dados!$D$44/BP!$C$13 -> 0.042780749 | D12: % | E12: =Dados!D44/BP!C13 | F12: Maior que o NPL 90 (2,9%) porque inclui reestruturados e outros sinais de problema.
A14: Por que a cobertura caiu? | B14: Em 2025 o NPL 90 quase dobrou (31.000 para 55.000) e a provisão subiu menos (82.000 para 108.000): cobertura de 265% para 196%. Ainda é confortável, mas a tendência pede atenção, junto com as renegociações (de 41.000 para 62.000).

Sheet Ex09
A1: Exercício 09: RWA e Índice de Basileia
A2: Tema: RWA e Basileia | valores em R$ mil, salvo indicação
A3: Use a aba RWA e as premissas de FPR (ilustrativas). Calcule o RWA e o índice de 2024, o índice de 2025 sem a LFS e o efeito de crescer R$ 200 mi de crédito comercial, pagos com a centralização.
A4: Dica: RWA de crédito = soma de exposição × FPR. RWA operacional (simplificado) = 15% × média da receita bruta de 3 anos ÷ 8%.
A6: Item | B6: Passo / pergunta | C6: Resultado | D6: Unidade | E6: Fórmula (Excel PT-BR) | F6: Como foi feito
A7: a | B7: RWA de crédito de 2024 | C7: =RWA!$D$18 -> 1791608 | D7: R$ mil | E7: =RWA!D18 | F7: Aba RWA: soma de cada exposição × FPR.
B8: Receita bruta média 2022 a 2024 | C8: =AVERAGE(Dados!$B$76,Dados!$B$77,Dados!$C$75) -> 195566.67 | D8: R$ mil | E8: =MÉDIA(Dados!B76;Dados!B77;Dados!C75) | F8: Receita bruta = margem financeira + serviços e tarifas.
A9: b | B9: RWA operacional de 2024 | C9: =Dados!$B$78*C8/Dados!$B$79 -> 366687.5 | D9: R$ mil | E9: =Dados!B78*C8/Dados!B79 | F9: 15% × média ÷ 8%.
B10: RWA total de 2024 | C10: =C7+C9+Dados!$C$73 -> 2161295.5 | D10: R$ mil | E10: =C7+C9+Dados!C73 | F10: Crédito + operacional + mercado.
B11: PR de 2024 | C11: =RWA!$D$28 -> 298540 | D11: R$ mil | E11: =RWA!D28 | F11: PL - intangível - outros ajustes + LFS (zero em 2024).
A12: c | B12: Índice de Basileia de 2024 | C12: =C11/C10 -> 0.13813012 | D12: % | E12: =C11/C10 | F12: PR ÷ RWA.
A13: d | B13: MM/RWA de 2024 | C13: =(C12-Dados!$B$80)*100 -> 3.3130117 | D13: p.p. | E13: =(C12-Dados!B80)*100 | F13: Folga sobre a exigência de 10,5%.
A14: e | B14: Basileia de 2025 sem a LFS | C14: =RWA!$F$26/RWA!$F$22 -> 0.13786282 | D14: % | E14: =RWA!F26/RWA!F22 | F14: Capital principal ÷ RWA: sem a LFS o índice teria caído.
A15: f | B15: Capital consumido por R$ 200 mi de crédito comercial | C15: =200000*Dados!$B$92*Dados!$B$80 -> 17850 | D15: R$ mil | E15: =200000*Dados!B92*Dados!B80 | F15: 200.000 × 85% × 10,5%.
B16: Novo RWA de 2025 | C16: =RWA!$F$22+200000*Dados!$B$92-200000*Dados!$B$89 -> 2604053.5 | D16: R$ mil | E16: =RWA!F22+200000*Dados!B92-200000*Dados!B89 | F16: Entra crédito com FPR 85% e sai centralização com FPR 20%.
A17: g | B17: Novo índice de Basileia de 2025 | C17: =RWA!$F$28/C16 -> 0.13674066 | D17: % | E17: =RWA!F28/C16 | F17: Mesmo PR, RWA maior.
A19: Leitura | B19: A cooperativa está acima da régua (MM/RWA perto de 3,9 p.p. em 2025), mas a folga veio da LFS. Crescer R$ 200 mi de crédito comercial tira cerca de 0,7 p.p. do índice. O PL precisa crescer junto com o RWA, e isso depende de resultado retido.

Sheet Ex10
A1: Exercício 10: Liquidez de 2024: LCR e indicadores internos
A2: Tema: Liquidez | valores em R$ mil, salvo indicação
A3: Com as premissas de estresse de 30 dias das notas, calcule o LCR didático de 2024 e os indicadores internos.
A4: Dica: Saídas líquidas = saídas - mínimo(entradas; 75% das saídas).
A6: Item | B6: Passo / pergunta | C6: Resultado | D6: Unidade | E6: Fórmula (Excel PT-BR) | F6: Como foi feito
A7: a | B7: Ativos líquidos de 2024 | C7: =BP!$B$6+BP!$B$9+BP!$B$7 -> 863540 | D7: R$ mil | E7: =BP!B6+BP!B9+BP!B7 | F7: Caixa + títulos públicos + centralização (resgatável).
A8: b | B8: Saídas em 30 dias de estresse | C8: =Indicadores!$C$80 -> 296100 | D8: R$ mil | E8: =Indicadores!C80 | F8: DV × 15% + poupança × 10% + RDC × 12% + LCA e obrigações que vencem + 5% dos limites + outras saídas.
B9: Entradas consideradas | C9: =Indicadores!$C$81 -> 92500 | D9: R$ mil | E9: =Indicadores!C81 | F9: 50% das parcelas a receber + aplicações que vencem, limitado a 75% das saídas.
A10: c | B10: LCR de 2024 | C10: =C7/(C8-C9) -> 4.2413556 | D10: % | E10: =C7/(C8-C9) | F10: Ativos líquidos ÷ saídas líquidas.
A11: d | B11: Índice de liquidez interno de 2024 | C11: =Dados!$C$15/(Dados!$B$83*BP!$B$28) -> 1.5950604 | D11: x | E11: =Dados!C15/(Dados!B83*BP!B28) | F11: Liquidez total ÷ (30% dos depósitos).
A12: e | B12: Crédito ÷ captação de 2024 | C12: =BP!$B$13/Dados!$C$25 -> 0.8 | D12: % | E12: =BP!B13/Dados!C25 | F12: Carteira ÷ (depósitos + LCA).
A13: f | B13: Liquidez imediata de 2024 | C13: =(BP!$B$6+BP!$B$7)/BP!$B$25 -> 1.8552308 | D13: x | E13: =(BP!B6+BP!B7)/BP!B25 | F13: Quantas vezes o caixa disponível cobre o depósito à vista.
A15: Leitura | B15: LCR acima de 400% e índice interno de 1,6: liquidez não é o problema. O ponto é o custo: dinheiro parado rende o CDI e a captação que o financia custa um pouco mais.

Sheet Ex11
A1: Exercício 11: FTP: quem gera a margem?
A2: Tema: FTP | valores em R$ mil, salvo indicação
A3: Use as taxas de transferência (FTP) de 2025 das notas. Calcule a margem de cada captação e responda: vale a pena pagar 105% do CDI no RDC para crescer captação?
A4: Dica: Margem da captação = saldo médio × FTP - despesa. Margem do crédito = receita - saldo médio × FTP.
A6: Item | B6: Passo / pergunta | C6: Resultado | D6: Unidade | E6: Fórmula (Excel PT-BR) | F6: Como foi feito
B7: Poupança média de 2025 | C7: =AVERAGE(Dados!$C$21,Dados!$D$21) -> 222500 | D7: R$ mil | E7: =MÉDIA(Dados!C21;Dados!D21)
A8: a | B8: Margem FTP da poupança | C8: =C7*Dados!$D$105+DSP!$C$13 -> 8200 | D8: R$ mil | E8: =C7*Dados!D105+DSP!C13 | F8: Recebe FTP de 12,0% e paga cerca de 8,3%: margem positiva.
B9: RDC médio de 2025 | C9: =AVERAGE(Dados!$C$22,Dados!$D$22) -> 1425000 | D9: R$ mil | E9: =MÉDIA(Dados!C22;Dados!D22)
A10: b | B10: Margem FTP do RDC | C10: =C9*Dados!$D$106+DSP!$C$14 -> -2125 | D10: R$ mil | E10: =C9*Dados!D106+DSP!C14 | F10: Recebe 100% do CDI e paga cerca de 101%: margem negativa.
A11: c | B11: Custo do RDC em % do CDI | C11: =-DSP!$C$14/C9/Dados!$D$5 -> 1.0104282 | D11: % | E11: =-DSP!C14/C9/Dados!D5 | F11: Despesa ÷ saldo médio ÷ CDI.
A12: d | B12: Custo a mais com RDC a 105% do CDI | C12: =C9*Dados!$D$5*1.05+DSP!$C$14 -> 8063.75 | D12: R$ mil | E12: =C9*Dados!D5*1,05+DSP!C14 | F12: Custo com 105% - custo atual.
A13: e | B13: Impacto no ROE (p.p.) | C13: =-C12/AVERAGE(Dados!$C$29,Dados!$D$29)*100 -> -2.463643 | D13: p.p. | E13: =-C12/MÉDIA(Dados!C29;Dados!D29)*100 | F13: Custo a mais ÷ PL médio.
A14: f | B14: Resultado da tesouraria (ALM) | C14: =Indicadores!$D$90 -> 41105 | D14: R$ mil | E14: =Indicadores!D90 | F14: Margem financeira - soma das margens dos produtos.
A16: Resposta | B16: Só vale pagar 105% do CDI se o dinheiro novo for para crédito com taxa que pague esse custo, a provisão e o capital. Se ficar parado na centralização (100% do CDI), cada real captado perde 5% do CDI por ano. O FTP mostra isso produto a produto.

Sheet Ex12
A1: Exercício 12: RAROC e taxa mínima de uma operação
A2: Tema: RAROC | valores em R$ mil, salvo indicação
A3: Operação PJ de R$ 500 mil por 1 ano: taxa de 21% a.a., FTP de 15%, custo operacional de 2,5% a.a., PD de 3%, LGD de 45%, FPR de 100%, capital alocado de 12,5% do RWA. O capital alocado é remunerado pela FTP. A meta (hurdle) é RAROC de 15%.
A4: Dica: Perda esperada = valor × PD × LGD. RAROC = (receita - FTP - custo operacional - perda esperada + crédito do capital) ÷ capital alocado.
A6: Item | B6: Passo / pergunta | C6: Resultado | D6: Unidade | E6: Fórmula (Excel PT-BR) | F6: Como foi feito
B7: Valor da operação | C7: 500 | D7: R$ mil | F7: Dado do enunciado.
A8: a | B8: Perda esperada = valor × PD × LGD | C8: =C7*3%*45% -> 6.75 | D8: R$ mil | E8: =C7*3%*45% | F8: 500 × 3% × 45% = 6,75.
A9: b | B9: Capital alocado = valor × FPR × 12,5% | C9: =C7*100%*12.5% -> 62.5 | D9: R$ mil | E9: =C7*100%*12,5% | F9: 500 × 100% × 12,5% = 62,5.
B10: Receita de juros (21%) | C10: =C7*21% -> 105 | D10: R$ mil | E10: =C7*21%
B11: (-) Custo de transferência (FTP 15%) | C11: =-C7*15% -> -75 | D11: R$ mil | E11: =-C7*15% | F11: O que a tesouraria cobra pelo dinheiro.
B12: (-) Custo operacional (2,5%) | C12: =-C7*2.5% -> -12.5 | D12: R$ mil | E12: =-C7*2,5%
B13: (+) Crédito do capital (capital × FTP) | C13: =C9*15% -> 9.375 | D13: R$ mil | E13: =C9*15% | F13: A parte financiada com capital não paga juros.
A14: c | B14: Resultado ajustado ao risco | C14: =C10+C11+C12-C8+C13 -> 20.125 | D14: R$ mil | E14: =C10+C11+C12-C8+C13 | F14: Receita - FTP - custo - PE + crédito do capital.
A15: d | B15: RAROC | C15: =C14/C9 -> 0.322 | D15: % | E15: =C14/C9 | F15: Resultado ajustado ÷ capital alocado.
A16: e | B16: Taxa mínima para RAROC de 15% | C16: =(15%*C9-C11-C12+C8-C13)/C7 -> 0.1885 | D16: % | E16: =(15%*C9-C11-C12+C8-C13)/C7 | F16: Isola a taxa: taxa × valor = 15% × capital + FTP + custo + PE - crédito do capital.
A18: Leitura | B18: A 21% a operação cria valor (RAROC de 32%). A taxa mínima é 18,85%: abaixo dela, a cooperativa remunera o capital do associado abaixo do custo de capital.

Sheet Ex13
A1: Exercício 13: Captação: mix e custo por produto
A2: Tema: Captação | valores em R$ mil, salvo indicação
A3: Calcule o mix de captação de 2025 e o custo implícito de cada produto. Depois calcule quanto custa por ano a migração de R$ 50 mi de depósito à vista para RDC a 101% do CDI.
A4: Dica: Custo implícito = despesa do produto ÷ saldo médio do produto.
A6: Item | B6: Passo / pergunta | C6: Resultado | D6: Unidade | E6: Fórmula (Excel PT-BR) | F6: Como foi feito
A7: a | B7: Depósito à vista ÷ captação 2025 | C7: =BP!$C$25/Dados!$D$25 -> 0.17710583 | D7: % | E7: =BP!C25/Dados!D25 | F7: DV ÷ (depósitos + LCA).
A8: b | B8: RDC ÷ captação 2025 | C8: =BP!$C$27/Dados!$D$25 -> 0.65658747 | D8: % | E8: =BP!C27/Dados!D25
A9: c | B9: Custo implícito da poupança | C9: =-DSP!$C$13/AVERAGE(Dados!$C$21,Dados!$D$21) -> 0.083146067 | D9: % | E9: =-DSP!C13/MÉDIA(Dados!C21;Dados!D21) | F9: Despesa ÷ saldo médio.
B10: Custo implícito da LCA | C10: =-DSP!$C$15/AVERAGE(Dados!$C$24,Dados!$D$24) -> 0.13185185 | D10: % | E10: =-DSP!C15/MÉDIA(Dados!C24;Dados!D24)
A11: d | B11: Custo da LCA em % do CDI | C11: =C10/Dados!$D$5 -> 0.92204092 | D11: % | E11: =C10/Dados!D5 | F11: LCA é isenta de IR para PF: paga menos que o CDI.
A12: e | B12: Custo anual da migração de R$ 50 mi de DV para RDC | C12: =50000*Dados!$D$5*1.01 -> 7221.5 | D12: R$ mil | E12: =50000*Dados!D5*1,01 | F12: 50.000 × 14,3% × 101%: o DV não custava nada.
A14: Leitura | B14: Perder depósito à vista é a forma mais silenciosa de perder margem: R$ 50 mi migrando custam R$ 7,2 mi por ano, cerca de 13% do resultado.

Sheet Ex14
A1: Exercício 14: Patrimônio líquido e destinação das sobras
A2: Tema: PL | valores em R$ mil, salvo indicação
A3: Use a DMPL de 2025 nas notas. Refaça o capital social e o PL de 31/12/2025 e analise a qualidade do capital.
A4: Dica: PL final = PL inicial + integralizações - devoluções + resultado - FATES - sobras distribuídas +/- ajustes. Juros ao capital incorporados entram no capital e saem do resultado: efeito zero no PL.
A6: Item | B6: Passo / pergunta | C6: Resultado | D6: Unidade | E6: Fórmula (Excel PT-BR) | F6: Como foi feito
A7: a | B7: Capital social em 31/12/2025 | C7: =DMPL!$B$16 -> 159870 | D7: R$ mil | E7: =DMPL!B16 | F7: 130.000 + 14.000 integralizações - 9.000 devoluções + 12.270 sobras capitalizadas + 12.600 juros ao capital incorporados.
A8: b | B8: PL em 31/12/2025 | C8: =DMPL!$F$16 -> 349080 | D8: R$ mil | E8: =DMPL!F16 | F8: Soma de todas as mutações. Confere com o BP.
B9: Capital médio de 2025 | C9: =AVERAGE(Dados!$C$30,Dados!$D$30) -> 144935 | D9: R$ mil | E9: =MÉDIA(Dados!C30;Dados!D30)
A10: c | B10: Juros ao capital em % do CDI | C10: =-DSP!$C$40/(C9*Dados!$D$5) -> 0.60794072 | D10: % | E10: =-DSP!C40/(C9*Dados!D5) | F10: Juros pagos ÷ (capital médio × CDI).
A11: d | B11: Capital social por associado (R$) | C11: =BP!$C$39*1000/Dados!$D$58 -> 1508.2075 | D11: R$ | E11: =BP!C39*1000/Dados!D58 | F11: R$ mil × 1.000 ÷ número de associados.
A12: e | B12: Capital social ÷ PL | C12: =BP!$C$39/BP!$C$43 -> 0.45797525 | D12: % | E12: =BP!C39/BP!C43 | F12: Parte do PL que pode sair com resgate de quotas.
A13: f | B13: Crescimento do PL - crescimento do RWA (p.p.) | C13: =(Dados!$D$29/Dados!$C$29-RWA!$F$22/RWA!$D$22)*100 -> -0.22067786 | D13: p.p. | E13: =(Dados!D29/Dados!C29-RWA!F22/RWA!D22)*100 | F13: Negativo: o risco cresceu um pouco mais rápido que o capital.
A15: Leitura | B15: Quase metade do PL é quota, que pode sair. As reservas são o capital estável. Para sustentar o crescimento, a cooperativa depende de reter sobras; distribuir em conta corrente ajuda o associado hoje, mas não fortalece o capital.

Sheet Ex15
A1: Exercício 15: Estudo de caso: o parecer da Coop Vale do Ipê
A2: Resposta modelo. Escreva o seu antes de ler.
A3: Escreva um parecer de uma página sobre a Coop Vale do Ipê, seguindo o roteiro de 10 passos. Responda: a cooperativa está saudável? O que melhorou, o que piorou, quais são os três riscos principais e quais as três recomendações para a diretoria? Compare depois com o parecer modelo (no HTML e na aba Ex15).
A5: 1. Conclusão | B5: A Coop Vale do Ipê é saudável, líquida e capitalizada acima do mínimo, mas a rentabilidade recorrente caiu forte em 2025 (ROE recorrente de 20,7% para 13,6%) e ficou abaixo do custo de capital de ~15%. A piora vem de três lugares: margem comprimida pelo CDI, risco de crédito subindo e captação mais cara.
A6: 2. Tamanho e crescimento | B6: Ativo de R$ 3.086.080 mil (+13,6%). Carteira de R$ 1.870.000 mil (+14,0%, 9,1% real). Crescimento equilibrado entre comercial (+14,3%) e rural (+13,5%).
A7: 3. Captação | B7: Captação de R$ 2.315.000 mil (+12,9%). O mix piorou: depósito à vista caiu para 17,7% e RDC subiu para 65,7%. O RDC custa 101,0% do CDI e tem margem FTP negativa.
A8: 4. Margem e spread | B8: Margem financeira de R$ 204.800 mil (+6,0%), mas o NIM caiu de 7,57% para 7,06% e o spread de crédito de 10,3 para 8,6 p.p. Motivo: captação reprecifica com o CDI na hora; a carteira pré, só no vencimento.
A9: 5. Eficiência | B9: IE contábil estável (58,5% para 59,1%), mas o recorrente piorou (57,5% para 59,8%). O IEAR subiu de 75,1% para 80,5%: o risco pesa mais que o custo.
A10: 6. Crédito | B10: NPL 90 subiu de 1,89% para 2,94%, a inadimplência de 15 a 90 dias também subiu e as renegociações cresceram 51%. Cobertura caiu de 265% para 196%. Custo do risco de 2,98% para 3,65% da carteira.
A11: 7. Capital | B11: Basileia de 13,81% para 14,39% (MM/RWA de 3,89 p.p.), mas sem a LFS seria 13,79%. O PL cresceu 14,3% e o RWA 14,5%. Potencial de crédito até o piso de 2 p.p.: cerca de R$ 340.533 mil.
A12: 8. Liquidez | B12: Folgada: índice interno de 1,62x, LCR didático de 430%, crédito/captação de 80,8%. Não é restrição; o excesso tem custo de carregamento.
A13: 9. Resultado recorrente | B13: Resultado de R$ 53.700 mil inclui R$ 9.200 mil não recorrentes (venda de imóvel, reversão de contingência, recuperação extraordinária). Recorrente: R$ 44.500 mil, queda de 26,7% contra 2024.
A14: 10. Três riscos | B14: (1) Risco de crédito em alta (NPL, estágio 3 e renegociações subindo juntos). (2) Margem: dependência crescente de RDC caro com carteira pré. (3) Capital: se o resultado recorrente continuar caindo, o PL deixa de acompanhar o RWA e a folga some.
A15: 11. Três recomendações | B15: (1) Rever a política de concessão e a cobrança das safras de 2024 e 2025, e acompanhar o estágio 2 todo mês. (2) Precificar o crédito novo pelo RAROC (taxa mínima por produto) e evitar pagar acima de 100% do CDI em RDC sem destino em crédito. (3) Priorizar retenção de sobras em reserva na AGO e planejar a substituição da LFS por capital próprio.

Sheet Gabarito
A1: Gabarito: todas as respostas numéricas
A2: Cada resposta é um link para a célula da aba do exercício
A4: Exercício | B4: Item | C4: Pergunta | D4: Resposta | E4: Unidade
A5: Ex02 | B5: a | C5: Depósitos a prazo (RDC) ÷ passivo + PL, em 2024 | D5: =Ex02!$C$9 -> 0.48941322 | E5: %
A6: Ex02 | B6: b | C6: Depósitos a prazo (RDC) ÷ passivo + PL, em 2025 | D6: =Ex02!$C$10 -> 0.49253422 | E6: %
A7: Ex02 | B7: c | C7: Depósitos à vista ÷ passivo + PL, em 2024 | D7: =Ex02!$C$11 -> 0.14351215 | E7: %
A8: Ex02 | B8: d | C8: Depósitos à vista ÷ passivo + PL, em 2025 | D8: =Ex02!$C$12 -> 0.13285462 | E8: %
A9: Ex02 | B9: e | C9: PL ÷ passivo + PL, em 2025 | D9: =Ex02!$C$13 -> 0.11311437 | E9: %
A10: Ex02 | B10: f | C10: Captação com associados (depósitos + LCA) ÷ passivo + PL, em 2025 | D10: =Ex02!$C$14 -> 0.75014258 | E10: %
A11: Ex03 | B11: a | C11: AH da receita de operações de crédito | D11: =Ex03!$C$7 -> 0.1873496 | E11: %
A12: Ex03 | B12: b | C12: AH da despesa de captação (operações de captação no mercado) | D12: =Ex03!$C$8 -> 0.48408408 | E12: %
A13: Ex03 | B13: c | C13: AH da margem financeira (visão gerencial) | D13: =Ex03!$C$9 -> 0.060041408 | E13: %
A14: Ex03 | B14: d | C14: AH da despesa de provisão para perdas (PDD) | D14: =Ex03!$C$10 -> 0.39130435 | E14: %
A15: Ex03 | B15: e | C15: AH do resultado antes dos juros ao capital | D15: =Ex03!$C$11 -> -0.082051282 | E15: %
A16: Ex04 | B16: a | C16: Margem financeira de 2024 (R$ mil) | D16: =Ex04!$C$7 -> 193200 | E16: R$ mil
A17: Ex04 | B17: b | C17: NIM de 2024 (margem ÷ ativo médio de 2023 e 2024) | D17: =Ex04!$C$9 -> 0.075652858 | E17: %
A18: Ex04 | B18: c | C18: NIM de 2025 | D18: =Ex04!$C$11 -> 0.07057664 | E18: %
A19: Ex04 | B19: d | C19: Variação do NIM de 2024 para 2025, em pontos percentuais | D19: =Ex04!$C$12 -> -0.50762182 | E19: p.p.
A20: Ex05 | B20: a | C20: Taxa média da carteira de crédito (receita de crédito ÷ carteira média) | D20: =Ex05!$C$8 -> 0.18828479 | E20: %
A21: Ex05 | B21: b | C21: Custo médio da captação, incluindo o depósito à vista a custo zero | D21: =Ex05!$C$11 -> 0.085149545 | E21: %
A22: Ex05 | B22: c | C22: Spread de crédito (a - b), em pontos percentuais | D22: =Ex05!$C$12 -> 10.313524 | E22: p.p.
A23: Ex05 | B23: d | C23: Custo médio só dos passivos onerosos (sem o depósito à vista) | D23: =Ex05!$C$13 -> 0.10578352 | E23: %
A24: Ex06 | B24: a | C24: ROE contábil de 2024 | D24: =Ex06!$C$9 -> 0.19981555 | E24: %
A25: Ex06 | B25: b | C25: Resultado recorrente de 2024 (R$ mil) | D25: =Ex06!$C$11 -> 60700 | E25: R$ mil
A26: Ex06 | B26: c | C26: ROE recorrente de 2024 | D26: =Ex06!$C$12 -> 0.20732999 | E26: %
A27: Ex06 | B27: d | C27: Margem: resultado ÷ receita líquida | D27: =Ex06!$C$13 -> 0.2480916 | E27: %
A28: Ex06 | B28: e | C28: Giro: receita líquida ÷ ativo médio | D28: =Ex06!$C$14 -> 0.092334079 | E28: %
A29: Ex06 | B29: f | C29: Alavancagem: ativo médio ÷ PL médio | D29: =Ex06!$C$15 -> 8.7227858 | E29: x
A30: Ex07 | B30: a | C30: IE de 2024 | D30: =Ex07!$C$8 -> 0.58524173 | E30: %
A31: Ex07 | B31: b | C31: IEAR de 2024 | D31: =Ex07!$C$9 -> 0.75063613 | E31: %
A32: Ex07 | B32: c | C32: IE recorrente de 2025 (sem a reversão de contingência na receita) | D32: =Ex07!$C$12 -> 0.59795437 | E32: %
A33: Ex07 | B33: d | C33: Corte de despesas administrativas em 2025 para o IE recorrente voltar ao IE recorrente de 2024 (R$ mil) | D33: =Ex07!$C$14 -> 5926.6327 | E33: R$ mil
A34: Ex08 | B34: a | C34: Inadimplência acima de 90 dias (NPL 90) em 2024 | D34: =Ex08!$C$7 -> 0.018902439 | E34: %
A35: Ex08 | B35: b | C35: Inadimplência de 15 a 90 dias em 2024 (sinal antecedente) | D35: =Ex08!$C$8 -> 0.02195122 | E35: %
A36: Ex08 | B36: c | C36: Cobertura: provisão ÷ carteira vencida há mais de 90 dias, 2024 | D36: =Ex08!$C$9 -> 2.6451613 | E36: %
A37: Ex08 | B37: d | C37: Custo do risco: despesa de PDD ÷ carteira média, 2024 | D37: =Ex08!$C$10 -> 0.029773463 | E37: %
A38: Ex08 | B38: e | C38: Baixas para prejuízo em 2024 (R$ mil), pela movimentação da provisão | D38: =Ex08!$C$11 -> 32000 | E38: R$ mil
A39: Ex08 | B39: f | C39: Participação do estágio 3 na carteira em 2025 | D39: =Ex08!$C$12 -> 0.042780749 | E39: %
A40: Ex09 | B40: a | C40: RWA de risco de crédito de 2024 (R$ mil) | D40: =Ex09!$C$7 -> 1791608 | E40: R$ mil
A41: Ex09 | B41: b | C41: RWA de risco operacional de 2024 (R$ mil) | D41: =Ex09!$C$9 -> 366687.5 | E41: R$ mil
A42: Ex09 | B42: c | C42: Índice de Basileia de 2024 | D42: =Ex09!$C$12 -> 0.13813012 | E42: %
A43: Ex09 | B43: d | C43: MM/RWA de 2024 (folga sobre 10,5%, em p.p.) | D43: =Ex09!$C$13 -> 3.3130117 | E43: p.p.
A44: Ex09 | B44: e | C44: Índice de Basileia de 2025 sem a LFS | D44: =Ex09!$C$14 -> 0.13786282 | E44: %
A45: Ex09 | B45: f | C45: Capital mínimo (10,5%) consumido por R$ 200 mi de crédito comercial com FPR 85% (R$ mil) | D45: =Ex09!$C$15 -> 17850 | E45: R$ mil
A46: Ex09 | B46: g | C46: Novo índice de Basileia de 2025 com esse crédito (sai da centralização, FPR 20%) | D46: =Ex09!$C$17 -> 0.13674066 | E46: %
A47: Ex10 | B47: a | C47: Ativos líquidos de alta qualidade (caixa + TVM + centralização), 2024 (R$ mil) | D47: =Ex10!$C$7 -> 863540 | E47: R$ mil
A48: Ex10 | B48: b | C48: Saídas de caixa no estresse de 30 dias (R$ mil) | D48: =Ex10!$C$8 -> 296100 | E48: R$ mil
A49: Ex10 | B49: c | C49: LCR de 2024 (ativos líquidos ÷ saídas líquidas) | D49: =Ex10!$C$10 -> 4.2413556 | E49: %
A50: Ex10 | B50: d | C50: Índice de liquidez interno: liquidez ÷ (30% dos depósitos) | D50: =Ex10!$C$11 -> 1.5950604 | E50: x
A51: Ex10 | B51: e | C51: Crédito ÷ captação (depósitos + LCA) | D51: =Ex10!$C$12 -> 0.8 | E51: %
A52: Ex10 | B52: f | C52: Liquidez imediata: (caixa + centralização) ÷ depósitos à vista | D52: =Ex10!$C$13 -> 1.8552308 | E52: x
A53: Ex11 | B53: a | C53: Margem FTP da poupança em 2025 (R$ mil) | D53: =Ex11!$C$8 -> 8200 | E53: R$ mil
A54: Ex11 | B54: b | C54: Margem FTP do RDC em 2025 (R$ mil) | D54: =Ex11!$C$10 -> -2125 | E54: R$ mil
A55: Ex11 | B55: c | C55: Custo implícito do RDC em % do CDI de 2025 | D55: =Ex11!$C$11 -> 1.0104282 | E55: %
A56: Ex11 | B56: d | C56: Custo anual a mais se todo o RDC médio pagasse 105% do CDI (R$ mil) | D56: =Ex11!$C$12 -> 8063.75 | E56: R$ mil
A57: Ex11 | B57: e | C57: Impacto desse custo no ROE de 2025, em p.p. | D57: =Ex11!$C$13 -> -2.463643 | E57: p.p.
A58: Ex11 | B58: f | C58: Resultado da tesouraria (ALM) que fecha a margem financeira de 2025 (R$ mil) | D58: =Ex11!$C$14 -> 41105 | E58: R$ mil
A59: Ex12 | B59: a | C59: Perda esperada (R$ mil) | D59: =Ex12!$C$8 -> 6.75 | E59: R$ mil
A60: Ex12 | B60: b | C60: Capital alocado (R$ mil) | D60: =Ex12!$C$9 -> 62.5 | E60: R$ mil
A61: Ex12 | B61: c | C61: Resultado ajustado ao risco (R$ mil) | D61: =Ex12!$C$14 -> 20.125 | E61: R$ mil
A62: Ex12 | B62: d | C62: RAROC da operação | D62: =Ex12!$C$15 -> 0.322 | E62: %
A63: Ex12 | B63: e | C63: Taxa mínima para o RAROC chegar a 15% | D63: =Ex12!$C$16 -> 0.1885 | E63: %
A64: Ex13 | B64: a | C64: Depósito à vista no total da captação de 2025 | D64: =Ex13!$C$7 -> 0.17710583 | E64: %
A65: Ex13 | B65: b | C65: RDC no total da captação de 2025 | D65: =Ex13!$C$8 -> 0.65658747 | E65: %
A66: Ex13 | B66: c | C66: Custo implícito da poupança em 2025 | D66: =Ex13!$C$9 -> 0.083146067 | E66: %
A67: Ex13 | B67: d | C67: Custo implícito da LCA em % do CDI | D67: =Ex13!$C$11 -> 0.92204092 | E67: %
A68: Ex13 | B68: e | C68: Custo anual da migração de R$ 50 mi de DV para RDC a 101% do CDI (R$ mil) | D68: =Ex13!$C$12 -> 7221.5 | E68: R$ mil
A69: Ex14 | B69: a | C69: Capital social em 31/12/2025 (R$ mil) | D69: =Ex14!$C$7 -> 159870 | E69: R$ mil
A70: Ex14 | B70: b | C70: PL em 31/12/2025 (R$ mil) | D70: =Ex14!$C$8 -> 349080 | E70: R$ mil
A71: Ex14 | B71: c | C71: Juros ao capital de 2025 em % do CDI (sobre o capital médio) | D71: =Ex14!$C$10 -> 0.60794072 | E71: %
A72: Ex14 | B72: d | C72: Capital social por associado em 2025 (R$) | D72: =Ex14!$C$11 -> 1508.2075 | E72: R$
A73: Ex14 | B73: e | C73: Capital social ÷ PL em 2025 | D73: =Ex14!$C$12 -> 0.45797525 | E73: %
A74: Ex14 | B74: f | C74: Crescimento do PL menos crescimento do RWA em 2025, em p.p. | D74: =Ex14!$C$13 -> -0.22067786 | E74: p.p.
